

{"MSG":"搜尋到資料有2筆","count":2,"licenseData":[{"LANDATA":[{"LANDESC":"高雄市前鎮區235地號","SEQ":"1"},{"LANDESC":"高雄市前鎮區236地號","SEQ":"2"}],"IMAGESTAT":"N","licenseStr_3":"(79)高市工建築字第H09006號","BUILDING_HEIGHT":"10.4Ｍ","BUILDING_NO":"0幢 1棟 地上 3 層 地下 0 層 共 1戶","ADRCOUNT":1,"licenseSeq":"079300013200000","licenseStr_1":"(79)高市工建築使字第01320號","issuedDate":"079/08/08","AREA_TOTAL":"騎樓：15.76㎡，其他：508.24㎡","ADRDATA":[{"SEQ":1,"ADDR":"806 高雄市前鎮區英德街780號"}],"address":"806 高雄市前鎮區英德街780號","P01NAME":"林謝桃？林偉煌","LANCOUNT":2,"countyId":"H00"},{"LANDATA":[{"LANDESC":"高雄市鳳山區1085-26地號","SEQ":"1"},{"LANDESC":"高雄市鳳山區1089-4地號","SEQ":"2"},{"LANDESC":"高雄市鳳山區1088-4地號","SEQ":"3"}],"IMAGESTAT":"N","licenseStr_3":"(77)高縣建局建管字第04587號","BUILDING_HEIGHT":"17.7Ｍ","BUILDING_NO":"幢 1棟 地上 5 層 地下 1 層 共 1戶","ADRCOUNT":1,"licenseSeq":"07930132000000000IH0","licenseStr_1":"(79)高縣建局建管字第01320號","issuedDate":"079/03/02","AREA_TOTAL":"騎樓：0㎡，其他：1615㎡","ADRDATA":[{"SEQ":1,"ADDR":"830 高雄市鳳山區新富路578號"}],"address":"830 高雄市鳳山區新富路578號","P01NAME":"台灣省警察電訊所 代理所長:喬雙峰","LANCOUNT":3,"countyId":"IH0"}]}


