

{"MSG":"搜尋到資料有2筆","count":2,"licenseData":[{"LANDATA":[{"LANDESC":"臺南市中西區臨安段609地號","SEQ":"1"}],"IMAGESTAT":"N","licenseStr_3":"(092)南工造字第1905號","BUILDING_HEIGHT":"15.65Ｍ","BUILDING_NO":"幢 1棟 地上 4 層 地下 0 層 共 4戶","ADRCOUNT":1,"licenseSeq":"09330027100000000IF0","licenseStr_1":"(93)南工使字第271號","issuedDate":"093/02/25","AREA_TOTAL":"騎樓：38.25㎡，其他：353.75㎡","ADRDATA":[{"SEQ":1,"ADDR":"700 臺南市中西區臨安路一段193號3樓"}],"address":"700 臺南市中西區臨安路一段193號3樓","P01NAME":"陳淑敏","LANCOUNT":1,"countyId":"IF0"},{"LANDATA":[{"LANDESC":"臺南市官田區番子田段24-1地號","SEQ":"1"},{"LANDESC":"臺南市官田區番子田段43-9地號","SEQ":"2"},{"LANDESC":"臺南市官田區番子田段44-3地號","SEQ":"3"},{"LANDESC":"臺南市官田區番子田段44-7地號","SEQ":"4"},{"LANDESC":"臺南市官田區番子田段45-3地號","SEQ":"5"},{"LANDESC":"臺南市官田區番子田段49-2地號","SEQ":"6"},{"LANDESC":"臺南市官田區番子田段50地號","SEQ":"7"},{"LANDESC":"臺南市官田區番子田段51-2地號","SEQ":"8"},{"LANDESC":"臺南市官田區番子田段72-2地號","SEQ":"9"},{"LANDESC":"臺南市官田區番子田段73-5地號","SEQ":"10"},{"LANDESC":"臺南市官田區番子田段83-12地號","SEQ":"11"},{"LANDESC":"臺南市官田區番子田段83-13地號","SEQ":"12"}],"IMAGESTAT":"N","licenseStr_3":"","BUILDING_HEIGHT":"17.7Ｍ","BUILDING_NO":"幢 1棟 地上 3 層 地下 0 層 共 1戶","ADRCOUNT":1,"licenseSeq":"09330027100IG0","licenseStr_1":"(093)南工局使字第00271號","issuedDate":"091/06/27","AREA_TOTAL":"騎樓：0㎡，其他：27762.9㎡","ADRDATA":[{"SEQ":1,"ADDR":"720 臺南市官田區中華路一段325號"}],"address":"720 臺南市官田區中華路一段325號","P01NAME":"台南縣政府 縣長:蘇煥智","LANCOUNT":12,"countyId":"IG0"}]}


