

{"MSG":"搜尋到資料有2筆","count":2,"licenseData":[{"LANDATA":[{"LANDESC":"臺南市南區新興段205-27地號","SEQ":"1"}],"IMAGESTAT":"N","licenseStr_3":"(085)南工造字第307號","BUILDING_HEIGHT":"7Ｍ","BUILDING_NO":"幢 1棟 地上 2 層 地下 0 層 共 1戶","ADRCOUNT":1,"licenseSeq":"08530143800000000IF0","licenseStr_1":"(85)南工使字第1438號","issuedDate":"085/08/20","AREA_TOTAL":"騎樓：0㎡，其他：98㎡","ADRDATA":[{"SEQ":1,"ADDR":" 長南街38號"}],"address":" 長南街38號","P01NAME":"林碧雲","LANCOUNT":1,"countyId":"IF0"},{"LANDATA":[{"LANDESC":"臺南市下營區營正段886-2地號","SEQ":"1"}],"IMAGESTAT":"N","licenseStr_3":"","BUILDING_HEIGHT":"10.5Ｍ","BUILDING_NO":"幢 1棟 地上 3 層 地下 0 層 共 1戶","ADRCOUNT":1,"licenseSeq":"08530143800IG0","licenseStr_1":"(085)南工局使字第01438號","issuedDate":"084/11/24","AREA_TOTAL":"騎樓：0㎡，其他：136㎡","ADRDATA":[{"SEQ":1,"ADDR":"735 臺南市下營區仁里村85-2號"}],"address":"735 臺南市下營區仁里村85-2號","P01NAME":"黃崑山","LANCOUNT":1,"countyId":"IG0"}]}


