

{"MSG":"搜尋到資料有1筆","count":1,"licenseData":[{"LANDATA":[{"LANDESC":"基隆市信義區福祿段777- 地號","SEQ":"1"}],"IMAGESTAT":"N","licenseStr_3":"(84)基府工建字第00243號","BUILDING_HEIGHT":"15Ｍ","BUILDING_NO":"幢 1棟 地上 5 層 地下 1 層 共 10戶","ADRCOUNT":2,"licenseSeq":"08630011500","licenseStr_1":"(86)基使字第00115號","issuedDate":"086/06/24","AREA_TOTAL":"騎樓：0㎡，其他：324.6㎡","ADRDATA":[{"SEQ":1,"ADDR":"201 基隆市信義區正信路12巷14號及2樓之至5"},{"SEQ":2,"ADDR":"201 基隆市信義區正信路12巷14號1及2樓之至5"}],"address":"201 基隆市信義區正信路12巷14號及2樓之至5","P01NAME":"","LANCOUNT":1,"countyId":"I10"}]}


