

{"MSG":"搜尋到資料有2筆","count":2,"licenseData":[{"LANDATA":[{"LANDESC":"臺中市西區麻園頭段0077-0025地號","SEQ":"1"},{"LANDESC":"臺中市西區麻園頭段0077-0026地號","SEQ":"2"},{"LANDESC":"臺中市西區麻園頭段0077-0027地號","SEQ":"3"},{"LANDESC":"臺中市西區麻園頭段0077-0028地號","SEQ":"4"},{"LANDESC":"臺中市西區麻園頭段0077-0058地號","SEQ":"5"},{"LANDESC":"臺中市西區麻園頭段0077-0059地號","SEQ":"6"}],"IMAGESTAT":"N","licenseStr_3":"83中工建建字第01614號","BUILDING_HEIGHT":"26.98Ｍ","BUILDING_NO":"幢 1棟 地上 9 層 地下 3 層 共 17戶","ADRCOUNT":17,"licenseSeq":"08530005600","licenseStr_1":"85中工建使字第00056號","issuedDate":"085/01/11","AREA_TOTAL":"騎樓：90.34㎡，其他：669.66㎡","ADRDATA":[{"SEQ":1,"ADDR":"403 臺中市西區忠明里17鄰忠誠街31號"},{"SEQ":2,"ADDR":"403 臺中市西區忠明里17鄰忠誠街29號"},{"SEQ":3,"ADDR":"403 臺中市西區忠明里17鄰忠誠街31號"},{"SEQ":4,"ADDR":"403 臺中市西區忠明里17鄰忠誠街35號"},{"SEQ":5,"ADDR":"403 臺中市西區忠明里17鄰忠誠街33號3樓之1"},{"SEQ":6,"ADDR":"403 臺中市西區忠明里17鄰忠誠街33號3樓之2"},{"SEQ":7,"ADDR":"403 臺中市西區忠明里17鄰忠誠街33號4樓之1"},{"SEQ":8,"ADDR":"403 臺中市西區忠明里17鄰忠誠街33號4樓之2"},{"SEQ":9,"ADDR":"403 臺中市西區忠明里17鄰忠誠街33號5樓之1"},{"SEQ":10,"ADDR":"403 臺中市西區忠明里17鄰忠誠街33號5樓之2"},{"SEQ":11,"ADDR":"403 臺中市西區忠明里17鄰忠誠街33號6樓之1"},{"SEQ":12,"ADDR":"403 臺中市西區忠明里17鄰忠誠街33號6樓之2"},{"SEQ":13,"ADDR":"403 臺中市西區忠明里17鄰忠誠街33號7樓之1"},{"SEQ":14,"ADDR":"403 臺中市西區忠明里17鄰忠誠街33號7樓之2"},{"SEQ":15,"ADDR":"403 臺中市西區忠明里17鄰忠誠街33號8樓之1"},{"SEQ":16,"ADDR":"403 臺中市西區忠明里17鄰忠誠街33號8樓之2"},{"SEQ":17,"ADDR":"403 臺中市西區忠明里17鄰忠誠街33號9樓"}],"address":"403 臺中市西區忠明里17鄰忠誠街31號","P01NAME":"","LANCOUNT":6,"countyId":"I80"},{"LANDATA":[{"LANDESC":"臺中市清水區田寮段下湳子小段95-7地號","SEQ":"1"}],"IMAGESTAT":"N","licenseStr_3":"(085)工建建字第56號","BUILDING_HEIGHT":"7.3Ｍ","BUILDING_NO":"幢 1棟 地上 2 層 地下  層 共 1戶","ADRCOUNT":1,"licenseSeq":"08530005600000000I90","licenseStr_1":"(85)工建使字第56號","issuedDate":"085/08/24","AREA_TOTAL":"騎樓：0㎡，其他：155㎡","ADRDATA":[{"SEQ":1,"ADDR":"436 臺中市清水區下湳里5鄰中山路500-5號"}],"address":"436 臺中市清水區下湳里5鄰中山路500-5號","P01NAME":"洪基勝","LANCOUNT":1,"countyId":"I90"}]}


