

{"MSG":"搜尋到資料有2筆","count":2,"licenseData":[{"LANDATA":[{"LANDESC":"高雄市三民區201地號","SEQ":"1"},{"LANDESC":"高雄市三民區202地號","SEQ":"2"}],"IMAGESTAT":"N","licenseStr_3":"(62)高市工都築字第H03476號","BUILDING_HEIGHT":"10.3Ｍ","BUILDING_NO":"0幢 1棟 地上 3 層 地下 0 層 共 1戶","ADRCOUNT":1,"licenseSeq":"063300018870003","licenseStr_1":"(63)高市工都築使字第01887號","issuedDate":"063/04/20","AREA_TOTAL":"騎樓：15.21㎡，其他：82.41㎡","ADRDATA":[{"SEQ":1,"ADDR":"806 高雄市前鎮區一心一路102號"}],"address":"806 高雄市前鎮區一心一路102號","P01NAME":"鄭枝水","LANCOUNT":2,"countyId":"H00"},{"LANDATA":"","IMAGESTAT":"N","licenseStr_3":"(62)建局都字第41684號","BUILDING_HEIGHT":"11.6Ｍ","BUILDING_NO":"幢 1棟 地上 3 層 地下  層 共 1戶","ADRCOUNT":1,"licenseSeq":"06330188700000000IH0","licenseStr_1":"(63)高縣建局都管字第1887號","issuedDate":"063/03/24","AREA_TOTAL":"騎樓：15.6㎡，其他：121.4㎡","ADRDATA":[{"SEQ":1,"ADDR":" 南興里三民路57號"}],"address":" 南興里三民路57號","P01NAME":"賴韋成","LANCOUNT":0,"countyId":"IH0"}]}


