

{"MSG":"搜尋到資料有3筆","licenseData":[{"licenseStr_1":"57使字第0062號","ADRDATA":[{"ADDR":"臺北市中山區南京東路二段７１號","SEQ":1}],"address":"臺北市中山區南京東路二段７１號","P01NAME":"臺灣建設股份有限公司林玉嘉","BUILDING_NO":"0幢 1棟 地上11層 地下0層 共0戶","IMAGEURL":"","IMAGESTAT":"N","LANCOUNT":6,"LANDATA":[{"SEQ":1,"LANDESC":"臺北市中山區中庄子段0147-0094號"},{"SEQ":2,"LANDESC":"臺北市中山區中庄子段0147-0095號"},{"SEQ":3,"LANDESC":"臺北市中山區中庄子段0147-0096號"},{"SEQ":4,"LANDESC":"臺北市中山區中庄子段0147-0103號"},{"SEQ":5,"LANDESC":"臺北市中山區中庄子段0147-0104號"},{"SEQ":6,"LANDESC":"臺北市中山區中庄子段0147-0130號"}],"ADRCOUNT":1,"issuedDate":"057/01/18","countyId":"G00","licenseSeq":"00041734","AREA_TOTAL":"騎樓：0㎡，其他：1147.39㎡","BUILDING_HEIGHT":"0Ｍ","licenseStr_3":"55建字第0126號"},{"licenseStr_1":"57使字第0062號","ADRDATA":[{"ADDR":"臺北市中山區南京東路二段７１號二樓","SEQ":1}],"address":"臺北市中山區南京東路二段７１號二樓","P01NAME":"三陽船務代理股份有限公司    代表人：賴其里","BUILDING_NO":"0幢 1棟 地上10層 地下1層 共0戶","IMAGEURL":"","IMAGESTAT":"N","LANCOUNT":1,"LANDATA":[{"SEQ":1,"LANDESC":"臺北市中山區吉林段二小段0782-0000號"}],"ADRCOUNT":1,"issuedDate":"088/02/11","countyId":"G00","licenseSeq":"00069872","AREA_TOTAL":"騎樓：0㎡，其他：1147.39㎡","BUILDING_HEIGHT":"0Ｍ","licenseStr_3":"55建字第0126號"},{"licenseStr_1":"57使字第0062號","ADRDATA":[{"ADDR":"臺北市中山區南京東路二段７１號一樓","SEQ":1}],"address":"臺北市中山區南京東路二段７１號一樓","P01NAME":"台建投資股份有限公司:林蔡卿卿","BUILDING_NO":"0幢 1棟 地上10層 地下1層 共0戶","IMAGEURL":"","IMAGESTAT":"N","LANCOUNT":1,"LANDATA":[{"SEQ":1,"LANDESC":"臺北市中山區吉林段二小段0782-0000號"}],"ADRCOUNT":1,"issuedDate":"090/09/11","countyId":"G00","licenseSeq":"00076495","AREA_TOTAL":"騎樓：0㎡，其他：1147.39㎡","BUILDING_HEIGHT":"0Ｍ","licenseStr_3":"55建字第0126號"}],"count":3}


