

{"MSG":"搜尋到資料有2筆","count":2,"licenseData":[{"LANDATA":[{"LANDESC":"臺南市安南區和業段245地號","SEQ":"1"}],"IMAGESTAT":"N","licenseStr_3":"(083)南工造字第813號","BUILDING_HEIGHT":"11.48Ｍ","BUILDING_NO":"幢 1棟 地上 1 層 地下 0 層 共 1戶","ADRCOUNT":1,"licenseSeq":"08430005300000000IF0","licenseStr_1":"(84)南工使字第53號","issuedDate":"084/01/06","AREA_TOTAL":"騎樓：0㎡，其他：753.93㎡","ADRDATA":[{"SEQ":1,"ADDR":" 開安路183號"}],"address":" 開安路183號","P01NAME":"正勝鐵材行負責人：方新吉","LANCOUNT":1,"countyId":"IF0"},{"LANDATA":[{"LANDESC":"","SEQ":"1"},{"LANDESC":"","SEQ":"1"}],"IMAGESTAT":"N","licenseStr_3":"","BUILDING_HEIGHT":"","BUILDING_NO":"幢 1棟 地上 0 層 地下 0 層 共 戶","ADRCOUNT":68,"licenseSeq":"08430005300IG0","licenseStr_1":"(84)南縣使字第00053號","issuedDate":"","AREA_TOTAL":"騎樓：0㎡，其他：0㎡","ADRDATA":[{"SEQ":1,"ADDR":"710 臺南市永康區文化路120號"},{"SEQ":2,"ADDR":"710 臺南市永康區文化路122號"},{"SEQ":3,"ADDR":"710 臺南市永康區文化路126號"},{"SEQ":4,"ADDR":"710 臺南市永康區文化路128巷6號"},{"SEQ":5,"ADDR":"710 臺南市永康區文化路128巷8號"},{"SEQ":6,"ADDR":"710 臺南市永康區文化路128巷10號"},{"SEQ":7,"ADDR":"710 臺南市永康區文化路128巷12號"},{"SEQ":8,"ADDR":"710 臺南市永康區文化路128巷14號"},{"SEQ":9,"ADDR":"710 臺南市永康區文化路128巷16號"},{"SEQ":10,"ADDR":"710 臺南市永康區文化路124號"},{"SEQ":11,"ADDR":"710 臺南市永康區文化路128巷2號2樓之1"},{"SEQ":12,"ADDR":"710 臺南市永康區文化路128巷4號2樓之1"},{"SEQ":13,"ADDR":"710 臺南市永康區文化路128巷2號2樓之2"},{"SEQ":14,"ADDR":"710 臺南市永康區文化路128巷4號2樓之2"},{"SEQ":15,"ADDR":"710 臺南市永康區文化路128巷2號3樓之1"},{"SEQ":16,"ADDR":"710 臺南市永康區文化路128巷2號3樓之2"},{"SEQ":17,"ADDR":"710 臺南市永康區文化路128巷2號3樓之3"},{"SEQ":18,"ADDR":"710 臺南市永康區文化路128巷2號3樓之4"},{"SEQ":19,"ADDR":"710 臺南市永康區文化路128巷2號3樓之5"},{"SEQ":20,"ADDR":"710 臺南市永康區文化路128巷2號3樓之6"},{"SEQ":21,"ADDR":"710 臺南市永康區文化路128巷2號3樓之7"},{"SEQ":22,"ADDR":"710 臺南市永康區文化路128巷2號3樓之14"},{"SEQ":23,"ADDR":"710 臺南市永康區文化路128巷2號3樓之13"},{"SEQ":24,"ADDR":"710 臺南市永康區文化路128巷2號3樓之12"},{"SEQ":25,"ADDR":"710 臺南市永康區文化路128巷2號3樓之11"},{"SEQ":26,"ADDR":"710 臺南市永康區文化路128巷2號3樓之10"},{"SEQ":27,"ADDR":"710 臺南市永康區文化路128巷2號3樓之9"},{"SEQ":28,"ADDR":"710 臺南市永康區文化路128巷2號3樓之8"},{"SEQ":29,"ADDR":"710 臺南市永康區文化路128巷2號4樓之3"},{"SEQ":30,"ADDR":"710 臺南市永康區文化路128巷2號4樓之2"},{"SEQ":31,"ADDR":"710 臺南市永康區文化路128巷2號4樓之1"},{"SEQ":32,"ADDR":"710 臺南市永康區文化路128巷4號4樓之4"},{"SEQ":33,"ADDR":"710 臺南市永康區文化路128巷4號4樓之5"},{"SEQ":34,"ADDR":"710 臺南市永康區文化路128巷4號4樓之6"},{"SEQ":35,"ADDR":"710 臺南市永康區文化路128巷4號4樓之3"},{"SEQ":36,"ADDR":"710 臺南市永康區文化路128巷4號4樓之2"},{"SEQ":37,"ADDR":"710 臺南市永康區文化路128巷4號4樓之1"},{"SEQ":38,"ADDR":"710 臺南市永康區文化路128巷2號5樓之3"},{"SEQ":39,"ADDR":"710 臺南市永康區文化路128巷2號5樓之2"},{"SEQ":40,"ADDR":"710 臺南市永康區文化路128巷2號5樓之1"},{"SEQ":41,"ADDR":"710 臺南市永康區文化路128巷4號5樓之4"},{"SEQ":42,"ADDR":"710 臺南市永康區文化路128巷4號5樓之5"},{"SEQ":43,"ADDR":"710 臺南市永康區文化路128巷4號5樓之6"},{"SEQ":44,"ADDR":"710 臺南市永康區文化路128巷4號5樓之3"},{"SEQ":45,"ADDR":"710 臺南市永康區文化路128巷4號5樓之2"},{"SEQ":46,"ADDR":"710 臺南市永康區文化路128巷4號5樓之1"},{"SEQ":47,"ADDR":"710 臺南市永康區文化路128巷2號6樓之3"},{"SEQ":48,"ADDR":"710 臺南市永康區文化路128巷2號6樓之2"},{"SEQ":49,"ADDR":"710 臺南市永康區文化路128巷2號6樓之1"},{"SEQ":50,"ADDR":"710 臺南市永康區文化路128巷4號6樓之4"},{"SEQ":51,"ADDR":"710 臺南市永康區文化路128巷4號6樓之5"},{"SEQ":52,"ADDR":"710 臺南市永康區文化路128巷4號6樓之6"},{"SEQ":53,"ADDR":"710 臺南市永康區文化路128巷4號6樓之3"},{"SEQ":54,"ADDR":"710 臺南市永康區文化路128巷4號6樓之2"},{"SEQ":55,"ADDR":"710 臺南市永康區文化路128巷4號6樓之1"},{"SEQ":56,"ADDR":"710 臺南市永康區文化路128巷2號7樓之3"},{"SEQ":57,"ADDR":"710 臺南市永康區文化路128巷2號7樓之2"},{"SEQ":58,"ADDR":"710 臺南市永康區文化路128巷2號7樓之1"},{"SEQ":59,"ADDR":"710 臺南市永康區文化路128巷4號7樓之4"},{"SEQ":60,"ADDR":"710 臺南市永康區文化路128巷4號7樓之5"},{"SEQ":61,"ADDR":"710 臺南市永康區文化路128巷4號7樓之6"},{"SEQ":62,"ADDR":"710 臺南市永康區文化路128巷4號7樓之3"},{"SEQ":63,"ADDR":"710 臺南市永康區文化路128巷4號7樓之2"},{"SEQ":64,"ADDR":"710 臺南市永康區文化路128巷4號7樓之1"},{"SEQ":65,"ADDR":"710 臺南市永康區文化路128巷2號8樓之3"},{"SEQ":66,"ADDR":"710 臺南市永康區文化路128巷2號8樓之2"},{"SEQ":67,"ADDR":"710 臺南市永康區文化路128巷2號8樓之1"},{"SEQ":68,"ADDR":"710 臺南市永康區文化路128巷4號8樓"}],"address":" ","P01NAME":"","LANCOUNT":2,"countyId":"IG0"}]}


