

{"MSG":"搜尋到資料有2筆","count":2,"licenseData":[{"LANDATA":[{"LANDESC":"臺南市安平區上鯤鯓段409地號","SEQ":"1"}],"IMAGESTAT":"N","licenseStr_3":"(080)南工造字第77318號","BUILDING_HEIGHT":"15Ｍ","BUILDING_NO":"幢 6棟 地上 5 層 地下 1 層 共 70戶","ADRCOUNT":1,"licenseSeq":"08430090100000000IF0","licenseStr_1":"(84)南工使字第901號","issuedDate":"084/04/26","AREA_TOTAL":"騎樓：0㎡，其他：2236.04㎡","ADRDATA":[{"SEQ":1,"ADDR":"708 臺南市安平區安平路446巷25弄24-3號"}],"address":"708 臺南市安平區安平路446巷25弄24-3號","P01NAME":"","LANCOUNT":1,"countyId":"IF0"},{"LANDATA":[{"LANDESC":"","SEQ":"1"},{"LANDESC":"","SEQ":"1"},{"LANDESC":"","SEQ":"1"},{"LANDESC":"","SEQ":"1"}],"IMAGESTAT":"N","licenseStr_3":"(083)南縣建字第04771號","BUILDING_HEIGHT":"13.5Ｍ","BUILDING_NO":"幢 1棟 地上 4 層 地下 0 層 共 1戶","ADRCOUNT":4,"licenseSeq":"08430090100IG0","licenseStr_1":"(084)南縣使字第00901號","issuedDate":"084/03/07","AREA_TOTAL":"騎樓：0㎡，其他：78.84㎡","ADRDATA":[{"SEQ":1,"ADDR":"730 臺南市新營區復興路620巷15弄15號"},{"SEQ":2,"ADDR":"730 臺南市新營區復興路682巷18號"},{"SEQ":3,"ADDR":"730 臺南市新營區復興路682巷20號"},{"SEQ":4,"ADDR":"730 臺南市新營區復興路620巷15弄17號"}],"address":"730 臺南市新營區復興路620巷15弄15號","P01NAME":"","LANCOUNT":4,"countyId":"IG0"}]}


