

{"MSG":"搜尋到資料有1筆","licenseData":[{"licenseStr_1":"73使字第1760號","ADRDATA":"","address":"","P01NAME":"高明善","BUILDING_NO":"0幢 0棟 地上0層 地下0層 共0戶","IMAGEURL":"","IMAGESTAT":"N","LANCOUNT":39,"LANDATA":[{"SEQ":1,"LANDESC":"臺北市內湖區新里族段十四分坡內小段0238-0004號"},{"SEQ":2,"LANDESC":"臺北市內湖區新里族段十四分坡內小段0245-0007號"},{"SEQ":3,"LANDESC":"臺北市內湖區新里族段十四分坡內小段0635-0000號"},{"SEQ":4,"LANDESC":"臺北市內湖區新里族段十四分坡內小段0636-0000號"},{"SEQ":5,"LANDESC":"臺北市內湖區新里族段十四分坡內小段0637-0000號"},{"SEQ":6,"LANDESC":"臺北市內湖區新里族段十四分坡內小段0638-0000號"},{"SEQ":7,"LANDESC":"臺北市內湖區新里族段十四分坡內小段0638-0001號"},{"SEQ":8,"LANDESC":"臺北市內湖區新里族段十四分坡內小段0638-0002號"},{"SEQ":9,"LANDESC":"臺北市內湖區新里族段十四分坡內小段0638-0003號"},{"SEQ":10,"LANDESC":"臺北市內湖區新里族段十四分坡內小段0638-0004號"},{"SEQ":11,"LANDESC":"臺北市內湖區新里族段十四分坡內小段0638-0005號"},{"SEQ":12,"LANDESC":"臺北市內湖區新里族段十四分坡內小段0638-0006號"},{"SEQ":13,"LANDESC":"臺北市內湖區新里族段十四分坡內小段0638-0007號"},{"SEQ":14,"LANDESC":"臺北市內湖區新里族段十四分坡內小段0638-0008號"},{"SEQ":15,"LANDESC":"臺北市內湖區新里族段十四分坡內小段0639-0000號"},{"SEQ":16,"LANDESC":"臺北市內湖區新里族段十四分坡內小段0639-0001號"},{"SEQ":17,"LANDESC":"臺北市內湖區新里族段十四分坡內小段0639-0002號"},{"SEQ":18,"LANDESC":"臺北市內湖區新里族段十四分坡內小段0645-0000號"},{"SEQ":19,"LANDESC":"臺北市內湖區新里族段十四分坡內小段0647-0000號"},{"SEQ":20,"LANDESC":"臺北市內湖區新里族段十四分坡內小段0651-0000號"},{"SEQ":21,"LANDESC":"臺北市內湖區新里族段十四分坡內小段0652-0000號"},{"SEQ":22,"LANDESC":"臺北市內湖區新里族段十四分坡內小段0652-0002號"},{"SEQ":23,"LANDESC":"臺北市內湖區新里族段十四分坡內小段0652-0003號"},{"SEQ":24,"LANDESC":"臺北市內湖區新里族段十四分坡內小段0652-0005號"},{"SEQ":25,"LANDESC":"臺北市內湖區新里族段十四分坡內小段0652-0009號"},{"SEQ":26,"LANDESC":"臺北市內湖區新里族段十四分坡內小段0652-0010號"},{"SEQ":27,"LANDESC":"臺北市內湖區新里族段十四分坡內小段0653-0000號"},{"SEQ":28,"LANDESC":"臺北市內湖區新里族段十四分坡內小段0654-0000號"},{"SEQ":29,"LANDESC":"臺北市內湖區新里族段十四分坡內小段0655-0000號"},{"SEQ":30,"LANDESC":"臺北市內湖區新里族段十四分坡內小段0655-0002號"},{"SEQ":31,"LANDESC":"臺北市內湖區新里族段十四分坡內小段0656-0000號"},{"SEQ":32,"LANDESC":"臺北市內湖區新里族段十四分坡內小段0656-0001號"},{"SEQ":33,"LANDESC":"臺北市內湖區新里族段十四分坡內小段0657-0000號"},{"SEQ":34,"LANDESC":"臺北市內湖區新里族段十四分坡內小段0659-0004號"},{"SEQ":35,"LANDESC":"臺北市內湖區新里族段十四分坡內小段0659-0005號"},{"SEQ":36,"LANDESC":"臺北市內湖區新里族段十四分坡內小段0659-0007號"},{"SEQ":37,"LANDESC":"臺北市內湖區新里族段十四分坡內小段0659-0008號"},{"SEQ":38,"LANDESC":"臺北市內湖區新里族段十四分坡內小段0659-0009號"},{"SEQ":39,"LANDESC":"臺北市內湖區新里族段十四分坡內小段0660-0000號"}],"ADRCOUNT":0,"issuedDate":"073/12/11","countyId":"G00","licenseSeq":"00019415","AREA_TOTAL":"騎樓：4481.38㎡，其他：42913.62㎡","BUILDING_HEIGHT":"0Ｍ","licenseStr_3":"73建字第0053號"}],"count":1}


