

{"MSG":"搜尋到資料有2筆","count":2,"licenseData":[{"LANDATA":[{"LANDESC":"臺中市東區旱溪段51-6地號","SEQ":"1"},{"LANDESC":"臺中市東區旱溪段7地號","SEQ":"2"}],"IMAGESTAT":"N","licenseStr_3":"74中工建建字第00159號","BUILDING_HEIGHT":"8.3Ｍ","BUILDING_NO":"幢 1棟 地上 2 層 地下  層 共 1戶","ADRCOUNT":1,"licenseSeq":"07430015900","licenseStr_1":"74中工建使字第00159號","issuedDate":"074/01/14","AREA_TOTAL":"騎樓：0㎡，其他：164.82㎡","ADRDATA":[{"SEQ":1,"ADDR":"401 臺中市東區十甲路186巷7號"}],"address":"401 臺中市東區十甲路186巷7號","P01NAME":"富程成衣廠 林順朋","LANCOUNT":2,"countyId":"I80"},{"LANDATA":[{"LANDESC":"臺中市太平區太平段505-10地號","SEQ":"1"},{"LANDESC":"臺中市太平區太平段505-35地號","SEQ":"2"},{"LANDESC":"臺中市太平區太平段505-137地號","SEQ":"3"},{"LANDESC":"臺中市太平區太平段663地號","SEQ":"4"},{"LANDESC":"臺中市太平區太平段664地號","SEQ":"5"},{"LANDESC":"臺中市太平區太平段664-1地號","SEQ":"6"}],"IMAGESTAT":"N","licenseStr_3":"(074)建都字第00159號","BUILDING_HEIGHT":"6.7Ｍ","BUILDING_NO":"幢 1棟 地上 2 層 地下  層 共 5戶","ADRCOUNT":5,"licenseSeq":"07430015900000000I90","licenseStr_1":"(74)建都使字第00159號","issuedDate":"074/07/10","AREA_TOTAL":"騎樓：21.92㎡，其他：521.96㎡","ADRDATA":[{"SEQ":1,"ADDR":"411 臺中市太平區太平村18鄰長億五街57巷17號"},{"SEQ":2,"ADDR":"411 臺中市太平區太平村18鄰長億五街57巷15號"},{"SEQ":3,"ADDR":"411 臺中市太平區太平村18鄰長億五街57巷13號"},{"SEQ":4,"ADDR":"411 臺中市太平區太平村18鄰長億五街57巷11號"},{"SEQ":5,"ADDR":"411 臺中市太平區太平村18鄰長億五街57巷19號"}],"address":"411 臺中市太平區太平村18鄰長億五街57巷17號","P01NAME":"長億實業股份有限公司 法定代理人：楊天生","LANCOUNT":6,"countyId":"I90"}]}


