

{"MSG":"搜尋到資料有1筆","count":1,"licenseData":[{"LANDATA":[{"LANDESC":"桃園縣八德市大湳段1221-3地號","SEQ":"1"},{"LANDESC":"桃園縣八德市大湳段1221-4地號","SEQ":"2"},{"LANDESC":"桃園縣八德市大湳段1221-5地號","SEQ":"3"},{"LANDESC":"桃園縣八德市大湳段1221-6地號","SEQ":"4"},{"LANDESC":"桃園縣八德市大湳段1221-7地號","SEQ":"5"},{"LANDESC":"桃園縣八德市大湳段1221-8地號","SEQ":"6"},{"LANDESC":"桃園縣八德市大湳段1221-9地號","SEQ":"7"},{"LANDESC":"桃園縣八德市大湳段1221-10地號","SEQ":"8"},{"LANDESC":"桃園縣八德市大湳段1221-11地號","SEQ":"9"},{"LANDESC":"桃園縣八德市大湳段1221-12地號","SEQ":"10"},{"LANDESC":"桃園縣八德市大湳段1221-13地號","SEQ":"11"},{"LANDESC":"桃園縣八德市大湳段1221-14地號","SEQ":"12"},{"LANDESC":"桃園縣八德市大湳段1221-15地號","SEQ":"13"},{"LANDESC":"桃園縣八德市大湳段1221-16地號","SEQ":"14"},{"LANDESC":"桃園縣八德市大湳段1221-17地號","SEQ":"15"}],"IMAGESTAT":"N","licenseStr_3":"(86)桃縣工建執照字第會00595號","BUILDING_HEIGHT":"13.7Ｍ","BUILDING_NO":"幢 2棟 地上 4 層 地下  層 共 13戶","ADRCOUNT":13,"licenseSeq":"08730091800I40","licenseStr_1":"(87)桃縣工建使字第德00918號","issuedDate":"087/08/12","AREA_TOTAL":"騎樓：0㎡，其他：1130.56㎡","ADRDATA":[{"SEQ":1,"ADDR":"334 桃園縣八德市大竹里7鄰榮興路8衖181巷31弄2號"},{"SEQ":2,"ADDR":"334 桃園縣八德市大竹里7鄰榮興路8衖181巷31弄6號"},{"SEQ":3,"ADDR":"334 桃園縣八德市大竹里7鄰榮興路8衖181巷31弄8號"},{"SEQ":4,"ADDR":"334 桃園縣八德市大竹里7鄰榮興路8衖181巷31弄10號"},{"SEQ":5,"ADDR":"334 桃園縣八德市大竹里7鄰榮興路8衖181巷31弄12號"},{"SEQ":6,"ADDR":"334 桃園縣八德市大竹里7鄰榮興路8衖181巷31弄14號"},{"SEQ":7,"ADDR":"334 桃園縣八德市大竹里7鄰榮興路8衖181巷31弄16號"},{"SEQ":8,"ADDR":"334 桃園縣八德市大竹里7鄰榮興路8衖181巷31弄1號"},{"SEQ":9,"ADDR":"334 桃園縣八德市大竹里7鄰榮興路8衖181巷31弄3號"},{"SEQ":10,"ADDR":"334 桃園縣八德市大竹里7鄰榮興路8衖181巷31弄5號"},{"SEQ":11,"ADDR":"334 桃園縣八德市大竹里7鄰榮興路8衖181巷31弄7號"},{"SEQ":12,"ADDR":"334 桃園縣八德市大竹里7鄰榮興路8衖181巷31弄9號"},{"SEQ":13,"ADDR":"334 桃園縣八德市大竹里7鄰榮興路8衖181巷31弄11號"}],"address":"334 桃園縣八德市大竹里7鄰榮興路8衖181巷31弄2號","P01NAME":"呂玉鶴.王林梅花","LANCOUNT":15,"countyId":"I40"}]}


