

{"MSG":"搜尋到資料有1筆","count":1,"licenseData":[{"LANDATA":[{"LANDESC":"新竹縣竹東鎮竹東段番社子小段403-3地號","SEQ":"1"},{"LANDESC":"新竹縣竹東鎮竹東段番社子小段403-9地號","SEQ":"2"},{"LANDESC":"新竹縣竹東鎮竹東段番社子小段406地號","SEQ":"3"},{"LANDESC":"新竹縣竹東鎮竹東段番社子小段407-2地號","SEQ":"4"},{"LANDESC":"新竹縣竹東鎮竹東段番社子小段69地號","SEQ":"5"},{"LANDESC":"新竹縣竹東鎮竹東段番社子小段7地號","SEQ":"6"},{"LANDESC":"新竹縣竹東鎮竹東段番社子小段7-5地號","SEQ":"7"}],"IMAGESTAT":"N","licenseStr_3":"(080)工建字第804號","BUILDING_HEIGHT":"36Ｍ","BUILDING_NO":"幢 1棟 地上 10 層 地下 1 層 共 138戶","ADRCOUNT":0,"licenseSeq":"08330049400","licenseStr_1":"(83)建都字第00494號","issuedDate":"083/05/06","AREA_TOTAL":"騎樓：228.9㎡，其他：2108.25㎡","ADRDATA":"","address":" ","P01NAME":"濱漢建設股份有限公司代表人：沈漢松","LANCOUNT":7,"countyId":"I60"}]}


