

{"MSG":"搜尋到資料有2筆","count":2,"licenseData":[{"LANDATA":[{"LANDESC":"臺中市北屯區仁美段1011-0地號","SEQ":"1"},{"LANDESC":"臺中市北屯區仁美段1011-9地號","SEQ":"2"},{"LANDESC":"臺中市北屯區仁美段1011-10地號","SEQ":"3"},{"LANDESC":"臺中市北屯區仁美段1011-11地號","SEQ":"4"},{"LANDESC":"臺中市北屯區仁美段1011-12地號","SEQ":"5"},{"LANDESC":"臺中市北屯區仁美段1011-13地號","SEQ":"6"},{"LANDESC":"臺中市北屯區仁美段1011-14地號","SEQ":"7"},{"LANDESC":"臺中市北屯區仁美段1011-15地號","SEQ":"8"},{"LANDESC":"臺中市北屯區仁美段1011-16地號","SEQ":"9"},{"LANDESC":"臺中市北屯區仁美段1011-17地號","SEQ":"10"},{"LANDESC":"臺中市北屯區仁美段1011-18地號","SEQ":"11"},{"LANDESC":"臺中市北屯區仁美段1011-19地號","SEQ":"12"},{"LANDESC":"臺中市北屯區仁美段1011-20地號","SEQ":"13"},{"LANDESC":"臺中市北屯區仁美段1011-21地號","SEQ":"14"},{"LANDESC":"臺中市北屯區仁美段1011-22地號","SEQ":"15"},{"LANDESC":"臺中市北屯區仁美段1011-23地號","SEQ":"16"},{"LANDESC":"臺中市北屯區仁美段1011-24地號","SEQ":"17"},{"LANDESC":"臺中市北屯區仁美段1011-25地號","SEQ":"18"},{"LANDESC":"臺中市北屯區仁美段1011-26地號","SEQ":"19"},{"LANDESC":"臺中市北屯區仁美段1011-27地號","SEQ":"20"},{"LANDESC":"臺中市北屯區仁美段1011-28地號","SEQ":"21"},{"LANDESC":"臺中市北屯區仁美段1011-29地號","SEQ":"22"},{"LANDESC":"臺中市北屯區仁美段1011-30地號","SEQ":"23"},{"LANDESC":"臺中市北屯區仁美段1011-31地號","SEQ":"24"},{"LANDESC":"臺中市北屯區仁美段1011-33地號","SEQ":"25"},{"LANDESC":"臺中市北屯區仁美段1011-34地號","SEQ":"26"}],"IMAGESTAT":"N","licenseStr_3":"98府都建建字第00724號","BUILDING_HEIGHT":"12.7Ｍ","BUILDING_NO":"3幢 25棟 地上 4 層 地下 0 層 共 25戶","ADRCOUNT":25,"licenseSeq":"09930059000","licenseStr_1":"99府都建使字第00590號","issuedDate":"099/11/08","AREA_TOTAL":"騎樓：0㎡，其他：2353.86㎡","ADRDATA":[{"SEQ":1,"ADDR":"406 臺中市北屯區仁美里3鄰長生巷27-2號"},{"SEQ":2,"ADDR":"406 臺中市北屯區仁美里3鄰長生巷27-3號"},{"SEQ":3,"ADDR":"406 臺中市北屯區仁美里3鄰長生巷27-5號"},{"SEQ":4,"ADDR":"406 臺中市北屯區仁美里3鄰長生巷27-6號"},{"SEQ":5,"ADDR":"406 臺中市北屯區仁美里3鄰長生巷27-7號"},{"SEQ":6,"ADDR":"406 臺中市北屯區仁美里3鄰長生巷27-8號"},{"SEQ":7,"ADDR":"406 臺中市北屯區仁美里3鄰長生巷27-9號"},{"SEQ":8,"ADDR":"406 臺中市北屯區仁美里3鄰長生巷27-10號"},{"SEQ":9,"ADDR":"406 臺中市北屯區仁美里3鄰長生巷27-21號"},{"SEQ":10,"ADDR":"406 臺中市北屯區仁美里3鄰長生巷27-20號"},{"SEQ":11,"ADDR":"406 臺中市北屯區仁美里3鄰長生巷27-19號"},{"SEQ":12,"ADDR":"406 臺中市北屯區仁美里3鄰長生巷27-18號"},{"SEQ":13,"ADDR":"406 臺中市北屯區仁美里3鄰長生巷27-17號"},{"SEQ":14,"ADDR":"406 臺中市北屯區仁美里3鄰長生巷27-16號"},{"SEQ":15,"ADDR":"406 臺中市北屯區仁美里3鄰長生巷27-15號"},{"SEQ":16,"ADDR":"406 臺中市北屯區仁美里3鄰長生巷27-13號"},{"SEQ":17,"ADDR":"406 臺中市北屯區仁美里3鄰長生巷27-12號"},{"SEQ":18,"ADDR":"406 臺中市北屯區仁美里3鄰長生巷27-11號"},{"SEQ":19,"ADDR":"406 臺中市北屯區仁美里3鄰長生巷27-22號"},{"SEQ":20,"ADDR":"406 臺中市北屯區仁美里3鄰長生巷27-23號"},{"SEQ":21,"ADDR":"406 臺中市北屯區仁美里3鄰長生巷27-25號"},{"SEQ":22,"ADDR":"406 臺中市北屯區仁美里3鄰長生巷27-26號"},{"SEQ":23,"ADDR":"406 臺中市北屯區仁美里3鄰長生巷27-27號"},{"SEQ":24,"ADDR":"406 臺中市北屯區仁美里3鄰長生巷27-28號"},{"SEQ":25,"ADDR":"406 臺中市北屯區仁美里3鄰長生巷27-29號"}],"address":"406 臺中市北屯區仁美里3鄰長生巷27-2號","P01NAME":"昌祐建設有限公司負責人:林文隆","LANCOUNT":26,"countyId":"I80"},{"LANDATA":[{"LANDESC":"臺中市龍井區忠和段798地號","SEQ":"1"}],"IMAGESTAT":"N","licenseStr_3":"","BUILDING_HEIGHT":"11.57Ｍ","BUILDING_NO":"1幢 1棟 地上 1 層 地下 0 層 共 1戶","ADRCOUNT":1,"licenseSeq":"09930059000I90","licenseStr_1":"(099)府工建使字第00590號","issuedDate":"099/11/01","AREA_TOTAL":"騎樓：0㎡，其他：1891.26㎡","ADRDATA":[{"SEQ":1,"ADDR":"434 臺中市龍井區龍津村21鄰蚵寮路328號"}],"address":"434 臺中市龍井區龍津村21鄰蚵寮路328號","P01NAME":"展輝工業有限公司負責人:陳春生","LANCOUNT":1,"countyId":"I90"}]}


