

{"MSG":"搜尋到資料有2筆","count":2,"licenseData":[{"LANDATA":[{"LANDESC":"高雄市三民區2697-11地號","SEQ":"1"}],"IMAGESTAT":"N","licenseStr_3":"(74)高市工建築字第D02191號","BUILDING_HEIGHT":"15Ｍ","BUILDING_NO":"0幢 1棟 地上 5 層 地下 0 層 共 5戶","ADRCOUNT":5,"licenseSeq":"075300022150000","licenseStr_1":"(75)高市工建築使字第02215號","issuedDate":"075/07/30","AREA_TOTAL":"騎樓：0㎡，其他：120.64㎡","ADRDATA":[{"SEQ":1,"ADDR":"807 高雄市三民區光武路152巷13號"},{"SEQ":2,"ADDR":"807 高雄市三民區光武路152巷13號2樓"},{"SEQ":3,"ADDR":"807 高雄市三民區光武路152巷13號3樓"},{"SEQ":4,"ADDR":"807 高雄市三民區光武路152巷13號4樓"},{"SEQ":5,"ADDR":"807 高雄市三民區光武路152巷13號5樓"}],"address":"807 高雄市三民區光武路152巷13號","P01NAME":"國泰建設股份有限公司 董事長蔡萬霖","LANCOUNT":1,"countyId":"H00"},{"LANDATA":[{"LANDESC":"高雄市橋頭區400-7地號","SEQ":"1"}],"IMAGESTAT":"N","licenseStr_3":"(74)高縣建局建管字第03539號","BUILDING_HEIGHT":"10.5Ｍ","BUILDING_NO":"幢 1棟 地上 3 層 地下 0 層 共 1戶","ADRCOUNT":1,"licenseSeq":"07530221500000000IH0","licenseStr_1":"(75)高縣建局建管字第02215號","issuedDate":"075/03/13","AREA_TOTAL":"騎樓：0㎡，其他：93㎡","ADRDATA":[{"SEQ":1,"ADDR":"825 高雄市橋頭區東林里東林路45-6號"}],"address":"825 高雄市橋頭區東林里東林路45-6號","P01NAME":"池燕聰","LANCOUNT":1,"countyId":"IH0"}]}


