

{"MSG":"搜尋到資料有8筆","count":8,"licenseData":[{"LANDATA":[{"LANDESC":"高雄市三民區151-2地號","SEQ":"1"}],"IMAGESTAT":"N","licenseStr_3":"(67)高市工都築字第D01931號","BUILDING_HEIGHT":"7.4Ｍ","BUILDING_NO":"0幢 1棟 地上 2 層 地下 0 層 共 1戶","ADRCOUNT":1,"licenseSeq":"067300072310003","licenseStr_1":"(67)高市工都築使字第07231號","issuedDate":"067/12/13","AREA_TOTAL":"騎樓：15.6㎡，其他：48.4㎡","ADRDATA":[{"SEQ":1,"ADDR":"807 高雄市三民區鼎金6巷43號"}],"address":"807 高雄市三民區鼎金6巷43號","P01NAME":"呂梅香","LANCOUNT":1,"countyId":"H00"},{"LANDATA":[{"LANDESC":"高雄市鳳山區1014地號","SEQ":"1"}],"IMAGESTAT":"N","licenseStr_3":"(67)高縣建局建管字第00088號","BUILDING_HEIGHT":"10.8Ｍ","BUILDING_NO":"幢 1棟 地上 3 層 地下  層 共 1戶","ADRCOUNT":1,"licenseSeq":"06731723100000000IH0","licenseStr_1":"(67)高縣建局建管字第17231號","issuedDate":"067/09/15","AREA_TOTAL":"騎樓：20.04㎡，其他：105.3㎡","ADRDATA":[{"SEQ":1,"ADDR":"830 高雄市鳳山區海洋二路69號"}],"address":"830 高雄市鳳山區海洋二路69號","P01NAME":"盧博樟","LANCOUNT":1,"countyId":"IH0"},{"LANDATA":[{"LANDESC":"高雄市鳳山區1014地號","SEQ":"1"}],"IMAGESTAT":"N","licenseStr_3":"(67)高縣建局建管字第00089號","BUILDING_HEIGHT":"10.8Ｍ","BUILDING_NO":"幢 1棟 地上 3 層 地下  層 共 1戶","ADRCOUNT":1,"licenseSeq":"06731723100000010IH0","licenseStr_1":"(67)高縣建局建管字第17231號-01","issuedDate":"067/09/15","AREA_TOTAL":"騎樓：16.02㎡，其他：61.07㎡","ADRDATA":[{"SEQ":1,"ADDR":"830 高雄市鳳山區海洋二路67號"}],"address":"830 高雄市鳳山區海洋二路67號","P01NAME":"曾榮欽","LANCOUNT":1,"countyId":"IH0"},{"LANDATA":[{"LANDESC":"高雄市鳳山區1014地號","SEQ":"1"}],"IMAGESTAT":"N","licenseStr_3":"(67)高縣建局建管字第00090號","BUILDING_HEIGHT":"10.8Ｍ","BUILDING_NO":"幢 1棟 地上 3 層 地下  層 共 1戶","ADRCOUNT":1,"licenseSeq":"06731723100000020IH0","licenseStr_1":"(67)高縣建局建管字第17231號-02","issuedDate":"067/09/15","AREA_TOTAL":"騎樓：16.02㎡，其他：61.07㎡","ADRDATA":[{"SEQ":1,"ADDR":"830 高雄市鳳山區海洋二路65號"}],"address":"830 高雄市鳳山區海洋二路65號","P01NAME":"許春金","LANCOUNT":1,"countyId":"IH0"},{"LANDATA":[{"LANDESC":"高雄市鳳山區1014地號","SEQ":"1"}],"IMAGESTAT":"N","licenseStr_3":"(67)高縣建局建管字第00091號","BUILDING_HEIGHT":"10.8Ｍ","BUILDING_NO":"幢 1棟 地上 3 層 地下  層 共 1戶","ADRCOUNT":1,"licenseSeq":"06731723100000030IH0","licenseStr_1":"(67)高縣建局建管字第17231號-03","issuedDate":"067/09/15","AREA_TOTAL":"騎樓：16.02㎡，其他：61.07㎡","ADRDATA":[{"SEQ":1,"ADDR":"830 高雄市鳳山區海洋二路63號"}],"address":"830 高雄市鳳山區海洋二路63號","P01NAME":"林瑞騰","LANCOUNT":1,"countyId":"IH0"},{"LANDATA":[{"LANDESC":"高雄市鳳山區1014地號","SEQ":"1"}],"IMAGESTAT":"N","licenseStr_3":"(67)高縣建局建管字第00092號","BUILDING_HEIGHT":"10.8Ｍ","BUILDING_NO":"幢 1棟 地上 3 層 地下  層 共 1戶","ADRCOUNT":1,"licenseSeq":"06731723100000040IH0","licenseStr_1":"(67)高縣建局建管字第17231號-04","issuedDate":"067/09/15","AREA_TOTAL":"騎樓：16.02㎡，其他：61.07㎡","ADRDATA":[{"SEQ":1,"ADDR":"830 高雄市鳳山區海洋二路61號"}],"address":"830 高雄市鳳山區海洋二路61號","P01NAME":"蔡盧金鳳","LANCOUNT":1,"countyId":"IH0"},{"LANDATA":[{"LANDESC":"高雄市鳳山區1014地號","SEQ":"1"}],"IMAGESTAT":"N","licenseStr_3":"(67)高縣建局建管字第00093號","BUILDING_HEIGHT":"10.8Ｍ","BUILDING_NO":"幢 1棟 地上 3 層 地下  層 共 1戶","ADRCOUNT":1,"licenseSeq":"06731723100000050IH0","licenseStr_1":"(67)高縣建局建管字第17231號-05","issuedDate":"067/09/15","AREA_TOTAL":"騎樓：16.02㎡，其他：61.07㎡","ADRDATA":[{"SEQ":1,"ADDR":"830 高雄市鳳山區海洋二路59號"}],"address":"830 高雄市鳳山區海洋二路59號","P01NAME":"郭玉花","LANCOUNT":1,"countyId":"IH0"},{"LANDATA":[{"LANDESC":"高雄市鳳山區1014地號","SEQ":"1"}],"IMAGESTAT":"N","licenseStr_3":"(67)高縣建局建管字第00091號","BUILDING_HEIGHT":"10.8Ｍ","BUILDING_NO":"幢 1棟 地上 3 層 地下 0 層 共 1戶","ADRCOUNT":1,"licenseSeq":"0673172310003","licenseStr_1":"(67)高縣建局都管字第17231號-03","issuedDate":"067/09/15","AREA_TOTAL":"騎樓：16.02㎡，其他：61.07㎡","ADRDATA":[{"SEQ":1,"ADDR":"830 高雄市鳳山區海洋二路63號"}],"address":"830 高雄市鳳山區海洋二路63號","P01NAME":"","LANCOUNT":1,"countyId":"IH0"}]}


