

{"MSG":"搜尋到資料有1筆","licenseData":[{"licenseStr_1":"69使字第0650號","ADRDATA":[{"ADDR":"null東園街６６巷２０弄３５之１號","SEQ":1},{"ADDR":"null東園街６６巷２０弄３５之１號","SEQ":2},{"ADDR":"null東園街６６巷２０弄３５之１號二樓","SEQ":3},{"ADDR":"null東園街６６巷２０弄３５之１號二樓","SEQ":4},{"ADDR":"null東園街６６巷２０弄３５之１號三樓","SEQ":5},{"ADDR":"null東園街６６巷２０弄３５之１號三樓","SEQ":6},{"ADDR":"null東園街６６巷２０弄３５之１號四樓","SEQ":7},{"ADDR":"null東園街６６巷２０弄３５之１號四樓","SEQ":8},{"ADDR":"null東園街６６巷２０弄３５之１號五樓","SEQ":9},{"ADDR":"null東園街６６巷２０弄３５之１號五樓","SEQ":10},{"ADDR":"null東園街６６巷２０弄３５之２號","SEQ":11},{"ADDR":"null東園街６６巷２０弄３５之２號","SEQ":12},{"ADDR":"null東園街６６巷２０弄３５之２號二樓","SEQ":13},{"ADDR":"null東園街６６巷２０弄３５之２號二樓","SEQ":14},{"ADDR":"null東園街６６巷２０弄３５之２號三樓","SEQ":15},{"ADDR":"null東園街６６巷２０弄３５之２號三樓","SEQ":16},{"ADDR":"null東園街６６巷２０弄３５之２號四樓","SEQ":17},{"ADDR":"null東園街６６巷２０弄３５之２號四樓","SEQ":18},{"ADDR":"null東園街６６巷２０弄３５之２號五樓","SEQ":19},{"ADDR":"null東園街６６巷２０弄３５之２號五樓","SEQ":20},{"ADDR":"null東園街６６巷２０弄３５之２號b1樓","SEQ":21},{"ADDR":"null東園街６６巷２０弄３５之２號b1樓","SEQ":22}],"address":"null東園街６６巷２０弄３５之１號","P01NAME":"陳寶鑾","BUILDING_NO":"0幢 1棟 地上5層 地下1層 共11戶","IMAGEURL":"","IMAGESTAT":"N","LANCOUNT":1,"LANDATA":[{"SEQ":1,"LANDESC":"null雙園段二小段0618-0000號"}],"ADRCOUNT":22,"issuedDate":"069/05/08","countyId":"G00","licenseSeq":"00028566","AREA_TOTAL":"騎樓：0㎡，其他：416.93㎡","BUILDING_HEIGHT":"15Ｍ","licenseStr_3":"67建字第0028號"}],"count":1}


