

{"MSG":"搜尋到資料有3筆","count":3,"licenseData":[{"LANDATA":[{"LANDESC":"桃園縣桃園市桃園段長美小段216-22地號","SEQ":"1"}],"IMAGESTAT":"N","licenseStr_3":"(067)第177號","BUILDING_HEIGHT":"18.8Ｍ","BUILDING_NO":"幢 1棟 地上 5 層 地下 1 層 共 2戶","ADRCOUNT":2,"licenseSeq":"0693H057900I40","licenseStr_1":"(69)桃縣建管使字第579號","issuedDate":"069/07/12","AREA_TOTAL":"騎樓：28.93㎡，其他：62.06㎡","ADRDATA":[{"SEQ":1,"ADDR":" 中山路189號"},{"SEQ":2,"ADDR":" 民族路153號"}],"address":" 中山路189號","P01NAME":"藍卓竹妹","LANCOUNT":1,"countyId":"I40"},{"LANDATA":[{"LANDESC":"桃園縣桃園市大樹林段788-1地號","SEQ":"1"},{"LANDESC":"桃園縣桃園市大樹林段788-32地號","SEQ":"2"},{"LANDESC":"桃園縣桃園市大樹林段788-33地號","SEQ":"3"},{"LANDESC":"桃園縣桃園市大樹林段788-34地號","SEQ":"4"},{"LANDESC":"桃園縣桃園市大樹林段788-35地號","SEQ":"5"},{"LANDESC":"桃園縣桃園市大樹林段788-36地號","SEQ":"6"},{"LANDESC":"桃園縣桃園市大樹林段788-38地號","SEQ":"7"},{"LANDESC":"桃園縣桃園市大樹林段788-60地號","SEQ":"8"},{"LANDESC":"桃園縣桃園市大樹林段806-3地號","SEQ":"9"},{"LANDESC":"桃園縣桃園市大樹林段806-5地號","SEQ":"10"},{"LANDESC":"桃園縣桃園市大樹林段806-6地號","SEQ":"11"},{"LANDESC":"桃園縣桃園市大樹林段806-7地號","SEQ":"12"}],"IMAGESTAT":"N","licenseStr_3":"(068)管工字第29號","BUILDING_HEIGHT":"8.05Ｍ","BUILDING_NO":"幢 1棟 地上 2 層 地下  層 共 戶","ADRCOUNT":1,"licenseSeq":"0693I057900I40","licenseStr_1":"(69)桃縣建管使工字第579號","issuedDate":"069/11/25","AREA_TOTAL":"騎樓：91.99㎡，其他：256.01㎡","ADRDATA":[{"SEQ":1,"ADDR":" 建國里林森路68巷20弄2號"}],"address":" 建國里林森路68巷20弄2號","P01NAME":"西北工業社 黃金生","LANCOUNT":12,"countyId":"I40"},{"LANDATA":"","IMAGESTAT":"N","licenseStr_3":"","BUILDING_HEIGHT":"","BUILDING_NO":"幢 棟 地上  層 地下  層 共 戶","ADRCOUNT":0,"licenseSeq":"0693M057900I40","licenseStr_1":"(69)中市都農使照字第00579號","issuedDate":"","AREA_TOTAL":"騎樓：0㎡，其他：0㎡","ADRDATA":"","address":"","P01NAME":"","LANCOUNT":0,"countyId":""}]}


