

{"MSG":"搜尋到資料有3筆","count":3,"licenseData":[{"LANDATA":[{"LANDESC":"臺中市南屯區惠禮段0198-0000地號","SEQ":"1"}],"IMAGESTAT":"N","licenseStr_3":"90中工建建字第00418號","BUILDING_HEIGHT":"13.3Ｍ","BUILDING_NO":"幢 1棟 地上 4 層 地下 0 層 共 1戶","ADRCOUNT":1,"licenseSeq":"09130017600","licenseStr_1":"91中工建使字第00176號","issuedDate":"091/03/13","AREA_TOTAL":"騎樓：0㎡，其他：136.49㎡","ADRDATA":[{"SEQ":1,"ADDR":"408 臺中市南屯區大墩六街319巷23號"}],"address":"408 臺中市南屯區大墩六街319巷23號","P01NAME":"王姿雯","LANCOUNT":1,"countyId":"I80"},{"LANDATA":[{"LANDESC":"臺中市神岡區順濟段230-1地號","SEQ":"1"}],"IMAGESTAT":"N","licenseStr_3":"(091)工建建字第176號","BUILDING_HEIGHT":"13.5Ｍ","BUILDING_NO":"幢 1棟 地上 4 層 地下  層 共 1戶","ADRCOUNT":1,"licenseSeq":"09130017600000000I90","licenseStr_1":"(91)府工建使字第176號","issuedDate":"094/06/10","AREA_TOTAL":"騎樓：14.18㎡，其他：64.81㎡","ADRDATA":[{"SEQ":1,"ADDR":"429 臺中市神岡區神岡村20鄰中正路22-1號"}],"address":"429 臺中市神岡區神岡村20鄰中正路22-1號","P01NAME":"E陳鴻明","LANCOUNT":1,"countyId":"I90"},{"LANDATA":[{"LANDESC":"臺中市神岡區順濟段230-1地號","SEQ":"1"},{"LANDESC":"臺中市神岡區順濟段230-4地號","SEQ":"2"},{"LANDESC":"臺中市神岡區順濟段230-6地號","SEQ":"3"},{"LANDESC":"臺中市神岡區順濟段231-3地號","SEQ":"4"},{"LANDESC":"臺中市神岡區順濟段231-4地號","SEQ":"5"},{"LANDESC":"臺中市神岡區順濟段231-9地號","SEQ":"6"}],"IMAGESTAT":"N","licenseStr_3":"91府工建建字第00176號","BUILDING_HEIGHT":"13.5Ｍ","BUILDING_NO":"幢 1棟 地上 4 層 地下  層 共 1戶","ADRCOUNT":1,"licenseSeq":"09130017600I90","licenseStr_1":"(91)府工建使字第176號","issuedDate":"094/06/10","AREA_TOTAL":"騎樓：14.18㎡，其他：64.81㎡","ADRDATA":[{"SEQ":1,"ADDR":"429 臺中市神岡區神岡村20鄰中正路22-1號"}],"address":"429 臺中市神岡區神岡村20鄰中正路22-1號","P01NAME":"E陳鴻明","LANCOUNT":6,"countyId":"I90"}]}


