

{"MSG":"搜尋到資料有2筆","count":2,"licenseData":[{"LANDATA":[{"LANDESC":"臺中市南屯區大新段732-1地號","SEQ":"1"}],"IMAGESTAT":"N","licenseStr_3":"75中工建建字第00781號","BUILDING_HEIGHT":"10Ｍ","BUILDING_NO":"幢 1棟 地上 3 層 地下  層 共 1戶","ADRCOUNT":1,"licenseSeq":"07530229800","licenseStr_1":"75中工建使字第02298號","issuedDate":"075/08/05","AREA_TOTAL":"騎樓：18.28㎡，其他：75.52㎡","ADRDATA":[{"SEQ":1,"ADDR":"408 臺中市南屯區大英街355號"}],"address":"408 臺中市南屯區大英街355號","P01NAME":"游英駿","LANCOUNT":1,"countyId":"I80"},{"LANDATA":[{"LANDESC":"臺中市清水區高美段2125地號","SEQ":"1"},{"LANDESC":"臺中市清水區高美段1600-2地號","SEQ":"2"},{"LANDESC":"臺中市清水區高美段1600-1地號","SEQ":"3"},{"LANDESC":"臺中市清水區田寮段下湳子小段220地號","SEQ":"4"}],"IMAGESTAT":"N","licenseStr_3":"(075)建管字第2298號","BUILDING_HEIGHT":"8.1Ｍ","BUILDING_NO":"幢 1棟 地上 2 層 地下  層 共 1戶","ADRCOUNT":1,"licenseSeq":"07530229800000000I90","licenseStr_1":"(75)建管使字第2298號","issuedDate":"075/12/03","AREA_TOTAL":"騎樓：0㎡，其他：691.59㎡","ADRDATA":[{"SEQ":1,"ADDR":"436 臺中市清水區下湳里17鄰中山路406-7號"}],"address":"436 臺中市清水區下湳里17鄰中山路406-7號","P01NAME":"洪潮良","LANCOUNT":4,"countyId":"I90"}]}


