

{"MSG":"搜尋到資料有2筆","count":2,"licenseData":[{"LANDATA":[{"LANDESC":"臺中市北區錦村段0191-0041地號","SEQ":"1"},{"LANDESC":"臺中市北區錦村段0191-0042地號","SEQ":"2"}],"IMAGESTAT":"N","licenseStr_3":"87中工建建字第00592號","BUILDING_HEIGHT":"12Ｍ","BUILDING_NO":"幢 1棟 地上 4 層 地下  層 共 1戶","ADRCOUNT":1,"licenseSeq":"08830069900","licenseStr_1":"88中工建使字第00699號","issuedDate":"088/06/08","AREA_TOTAL":"騎樓：0㎡，其他：114.24㎡","ADRDATA":[{"SEQ":1,"ADDR":"404 臺中市北區錦洲里5鄰瑞祥街74巷3弄2號"}],"address":"404 臺中市北區錦洲里5鄰瑞祥街74巷3弄2號","P01NAME":"張明山","LANCOUNT":2,"countyId":"I80"},{"LANDATA":[{"LANDESC":"臺中市大甲區永信段395地號","SEQ":"1"}],"IMAGESTAT":"N","licenseStr_3":"(088)工建建字第699號","BUILDING_HEIGHT":"7Ｍ","BUILDING_NO":"幢 1棟 地上 2 層 地下  層 共 1戶","ADRCOUNT":1,"licenseSeq":"08830069900000000I90","licenseStr_1":"(88)工建使字第699號","issuedDate":"088/09/07","AREA_TOTAL":"騎樓：0㎡，其他：801.5㎡","ADRDATA":[{"SEQ":1,"ADDR":"437 臺中市大甲區頂店里1鄰中山路一段1318號"}],"address":"437 臺中市大甲區頂店里1鄰中山路一段1318號","P01NAME":"薛榮定","LANCOUNT":1,"countyId":"I90"}]}


