

{"MSG":"搜尋到資料有1筆","count":1,"licenseData":[{"LANDATA":[{"LANDESC":"苗栗縣苗栗市社寮岡段180-3地號","SEQ":"1"},{"LANDESC":"苗栗縣苗栗市社寮岡段181-2地號","SEQ":"2"}],"IMAGESTAT":"N","licenseStr_3":"","BUILDING_HEIGHT":"6.88Ｍ","BUILDING_NO":"幢 1棟 地上 2 層 地下  層 共 2戶","ADRCOUNT":2,"licenseSeq":"0673005280066","licenseStr_1":"(67)栗建都苗字第528號","issuedDate":"067/11/27","AREA_TOTAL":"騎樓：0㎡，其他：244.2㎡","ADRDATA":[{"SEQ":1,"ADDR":"360 苗栗縣苗栗市北苗里19鄰自治路206號"},{"SEQ":2,"ADDR":"360 苗栗縣苗栗市北苗里19鄰自治路208號"}],"address":"360 苗栗縣苗栗市北苗里19鄰自治路206號","P01NAME":"張育生 張李梅蘭","LANCOUNT":2,"countyId":"I70"}]}


