

{"MSG":"搜尋到資料有1筆","licenseData":[{"licenseStr_1":"56使字第0006號","ADRDATA":[{"ADDR":"臺北市中山區雙城街３２巷４之２號","SEQ":1},{"ADDR":"臺北市中山區雙城街３２巷４號","SEQ":2}],"address":"臺北市中山區雙城街３２巷４號","P01NAME":"張周慈玉","BUILDING_NO":"0幢 1棟 地上4層 地下0層 共0戶","IMAGEURL":"","IMAGESTAT":"N","LANCOUNT":1,"LANDATA":[{"SEQ":1,"LANDESC":"臺北市中山區牛埔段0481-0007號"}],"ADRCOUNT":2,"issuedDate":"056/01/05","countyId":"G00","licenseSeq":"00040114","AREA_TOTAL":"騎樓：0㎡，其他：260.28㎡","BUILDING_HEIGHT":"0Ｍ","licenseStr_3":"55建字第0023號"}],"count":1}


