

{"MSG":"搜尋到資料有2筆","count":2,"licenseData":[{"LANDATA":[{"LANDESC":"高雄市楠梓區188-305地號","SEQ":"1"},{"LANDESC":"高雄市楠梓區188-306地號","SEQ":"2"},{"LANDESC":"高雄市楠梓區188-307地號","SEQ":"3"},{"LANDESC":"高雄市楠梓區188-308地號","SEQ":"4"},{"LANDESC":"高雄市楠梓區188-309地號","SEQ":"5"}],"IMAGESTAT":"N","licenseStr_3":"(98)高市工建築字第00351號","BUILDING_HEIGHT":"14.8Ｍ","BUILDING_NO":"1幢 5棟 地上 4 層 地下 0 層 共 5戶","ADRCOUNT":5,"licenseSeq":"099300001630000","licenseStr_1":"(99)高市工建築使字第00163號","issuedDate":"099/03/15","AREA_TOTAL":"騎樓：0㎡，其他：519.24㎡","ADRDATA":[{"SEQ":1,"ADDR":"811 高雄市楠梓區清豐三路173號"},{"SEQ":2,"ADDR":"811 高雄市楠梓區清豐三路175號"},{"SEQ":3,"ADDR":"811 高雄市楠梓區清豐三路177號"},{"SEQ":4,"ADDR":"811 高雄市楠梓區清豐三路179號"},{"SEQ":5,"ADDR":"811 高雄市楠梓區清豐三路181號"}],"address":"811 高雄市楠梓區清豐三路173號","P01NAME":"台灣糖業股份有限公司　負責人：胡懋麟","LANCOUNT":5,"countyId":"H00"},{"LANDATA":[{"LANDESC":"高雄市燕巢區179-1地號","SEQ":"1"}],"IMAGESTAT":"N","licenseStr_3":"(98)高縣建造字第00505號","BUILDING_HEIGHT":"6Ｍ","BUILDING_NO":"1幢 1棟 地上 1 層 地下 0 層 共 1戶","ADRCOUNT":1,"licenseSeq":"0993001630000","licenseStr_1":"(99)高縣建使字第00163號","issuedDate":"099/02/06","AREA_TOTAL":"騎樓：0㎡，其他：19994.65㎡","ADRDATA":[{"SEQ":1,"ADDR":"824 高雄市燕巢區鳳雄村20鄰高鐵總廠路59號"}],"address":"824 高雄市燕巢區鳳雄村20鄰高鐵總廠路59號","P01NAME":"賴錫堯","LANCOUNT":1,"countyId":"IH0"}]}


