

{"MSG":"搜尋到資料有7筆","count":7,"licenseData":[{"LANDATA":[{"LANDESC":"","SEQ":"1"},{"LANDESC":"","SEQ":"1"},{"LANDESC":"高雄市新興區306-23地號","SEQ":"2"}],"IMAGESTAT":"N","licenseStr_3":"(64)高市工都築字第03093號","BUILDING_HEIGHT":"32.28Ｍ","BUILDING_NO":"0幢 1棟 地上 10 層 地下 1 層 共 10戶","ADRCOUNT":4,"licenseSeq":"065300052770003","licenseStr_1":"(65)高市工都築使字第05277號","issuedDate":"065/11/24","AREA_TOTAL":"騎樓：66.3㎡，其他：587.16㎡","ADRDATA":[{"SEQ":1,"ADDR":"800 高雄市新興區中山一路117號"},{"SEQ":2,"ADDR":"800 高雄市新興區中山一路117號6樓"},{"SEQ":3,"ADDR":"800 高雄市新興區中山一路117號8樓"},{"SEQ":4,"ADDR":"800 高雄市新興區中山一路117號10樓"}],"address":"800 高雄市新興區中山一路117號","P01NAME":"","LANCOUNT":3,"countyId":"H00"},{"LANDATA":[{"LANDESC":"高雄市新興區306地號","SEQ":"1"},{"LANDESC":"高雄市新興區306-23地號","SEQ":"2"}],"IMAGESTAT":"N","licenseStr_3":"(64)高市工都築字第03093號","BUILDING_HEIGHT":"","BUILDING_NO":"幢 棟 地上  層 地下  層 共 戶","ADRCOUNT":1,"licenseSeq":"065300052770103","licenseStr_1":"(65)高市工都築變使字第05277-01號","issuedDate":"075/03/06","AREA_TOTAL":"騎樓：66.3㎡，其他：587.16㎡","ADRDATA":[{"SEQ":1,"ADDR":"800 高雄市新興區中山一路117號"}],"address":"800 高雄市新興區中山一路117號","P01NAME":"林文益.盧利吉","LANCOUNT":2,"countyId":"H00"},{"LANDATA":[{"LANDESC":"高雄市新興區1677地號","SEQ":"1"},{"LANDESC":"高雄市新興區1678地號","SEQ":"2"}],"IMAGESTAT":"N","licenseStr_3":"(65)高市工都築變使字第05277-01號","BUILDING_HEIGHT":"32.28Ｍ","BUILDING_NO":"0幢 1棟 地上 10 層 地下 1 層 共 1戶","ADRCOUNT":10,"licenseSeq":"065300052770203","licenseStr_1":"(65)高市工都築變使字第05277-02號","issuedDate":"078/06/30","AREA_TOTAL":"騎樓：66.3㎡，其他：587.16㎡","ADRDATA":[{"SEQ":1,"ADDR":"800 高雄市新興區中山一路117號"},{"SEQ":2,"ADDR":"800 高雄市新興區中山一路117號2樓"},{"SEQ":3,"ADDR":"800 高雄市新興區中山一路117號3樓"},{"SEQ":4,"ADDR":"800 高雄市新興區中山一路117號4樓"},{"SEQ":5,"ADDR":"800 高雄市新興區中山一路117號5樓"},{"SEQ":6,"ADDR":"800 高雄市新興區中山一路117號6樓"},{"SEQ":7,"ADDR":"800 高雄市新興區中山一路117號7樓"},{"SEQ":8,"ADDR":"800 高雄市新興區中山一路117號8樓"},{"SEQ":9,"ADDR":"800 高雄市新興區中山一路117號9樓"},{"SEQ":10,"ADDR":"800 高雄市新興區中山一路117號10樓"}],"address":"800 高雄市新興區中山一路117號","P01NAME":"","LANCOUNT":2,"countyId":"H00"},{"LANDATA":[{"LANDESC":"高雄市新興區1677地號","SEQ":"1"},{"LANDESC":"高雄市新興區1678地號","SEQ":"2"}],"IMAGESTAT":"N","licenseStr_3":"(64)高市工都築字第03093號","BUILDING_HEIGHT":"","BUILDING_NO":"幢 棟 地上  層 地下  層 共 戶","ADRCOUNT":1,"licenseSeq":"065300052770303","licenseStr_1":"(65)高市工都築變使字第05277-03號","issuedDate":"080/11/11","AREA_TOTAL":"騎樓：66.3㎡，其他：573.7㎡","ADRDATA":[{"SEQ":1,"ADDR":"800 高雄市新興區中山一路117號"}],"address":"800 高雄市新興區中山一路117號","P01NAME":"黃承志","LANCOUNT":2,"countyId":"H00"},{"LANDATA":[{"LANDESC":"高雄市新興區1677地號","SEQ":"1"},{"LANDESC":"高雄市新興區1678地號","SEQ":"2"}],"IMAGESTAT":"N","licenseStr_3":"(64)高市工都築字第03093號","BUILDING_HEIGHT":"","BUILDING_NO":"幢 棟 地上  層 地下  層 共 戶","ADRCOUNT":3,"licenseSeq":"065300052770403","licenseStr_1":"(65)高市工都築變使字第05277-04號","issuedDate":"082/12/14","AREA_TOTAL":"騎樓：66.3㎡，其他：587.16㎡","ADRDATA":[{"SEQ":1,"ADDR":"800 高雄市新興區中山一路117號"},{"SEQ":2,"ADDR":"800 高雄市新興區中山一路117號2樓"},{"SEQ":3,"ADDR":"800 高雄市新興區中山一路117號3樓"}],"address":"800 高雄市新興區中山一路117號","P01NAME":"","LANCOUNT":2,"countyId":"H00"},{"LANDATA":[{"LANDESC":"高雄市仁武區177-5地號","SEQ":"1"}],"IMAGESTAT":"N","licenseStr_3":"(64)高縣建局都管字第01111號","BUILDING_HEIGHT":"7Ｍ","BUILDING_NO":"幢 1棟 地上 2 層 地下  層 共 1戶","ADRCOUNT":1,"licenseSeq":"06530527700000000IH0","licenseStr_1":"(65)高縣建局都管字第5277號","issuedDate":"065/04/01","AREA_TOTAL":"騎樓：0㎡，其他：64㎡","ADRDATA":[{"SEQ":1,"ADDR":"814 高雄市仁武區竹後里閤興2巷3號"}],"address":"814 高雄市仁武區竹後里閤興2巷3號","P01NAME":"葉阿好","LANCOUNT":1,"countyId":"IH0"},{"LANDATA":[{"LANDESC":"高雄市梓官區252-5地號","SEQ":"1"}],"IMAGESTAT":"N","licenseStr_3":"(64)高縣建局都管字第02667號","BUILDING_HEIGHT":"7.6Ｍ","BUILDING_NO":"幢 1棟 地上 2 層 地下  層 共 1戶","ADRCOUNT":1,"licenseSeq":"06531527700000000IH0","licenseStr_1":"(65)高縣建局都管字第15277號","issuedDate":"065/08/24","AREA_TOTAL":"騎樓：16.54㎡，其他：127.86㎡","ADRDATA":[{"SEQ":1,"ADDR":"826 高雄市梓官區梓義里中崙路108號"}],"address":"826 高雄市梓官區梓義里中崙路108號","P01NAME":"凌清政","LANCOUNT":1,"countyId":"IH0"}]}


