

{"MSG":"搜尋到資料有1筆","count":1,"licenseData":[{"LANDATA":[{"LANDESC":"新竹縣竹東鎮仁愛段628地號","SEQ":"1"},{"LANDESC":"新竹縣竹東鎮仁愛段629-1地號","SEQ":"2"},{"LANDESC":"新竹縣竹東鎮仁愛段631地號","SEQ":"3"}],"IMAGESTAT":"N","licenseStr_3":"(095)府建字第00467號(02)","BUILDING_HEIGHT":"19.8Ｍ","BUILDING_NO":"2幢 2棟 地上 6 層 地下 0 層 共 30戶","ADRCOUNT":30,"licenseSeq":"09730058000","licenseStr_1":"(097)府使字第00580號","issuedDate":"097/08/20","AREA_TOTAL":"騎樓：25.74㎡，其他：1101.26㎡","ADRDATA":[{"SEQ":1,"ADDR":"310 新竹縣竹東鎮                林里大同路259-1號2樓"},{"SEQ":2,"ADDR":"310 新竹縣竹東鎮雞林里大同路259-1號3樓"},{"SEQ":3,"ADDR":"310 新竹縣竹東鎮雞林里大同路259-1號4樓"},{"SEQ":4,"ADDR":"310 新竹縣竹東鎮雞林里大同路259-1號5樓"},{"SEQ":5,"ADDR":"310 新竹縣竹東鎮雞林里大同路259-1號6樓"},{"SEQ":6,"ADDR":"310 新竹縣竹東鎮雞林里大同路261-1號2樓"},{"SEQ":7,"ADDR":"310 新竹縣竹東鎮雞林里大同路261-1號3樓"},{"SEQ":8,"ADDR":"310 新竹縣竹東鎮雞林里大同路261-1號4樓"},{"SEQ":9,"ADDR":"310 新竹縣竹東鎮雞林里大同路261-1號5樓"},{"SEQ":10,"ADDR":"310 新竹縣竹東鎮雞林里大同路261-1號6樓"},{"SEQ":11,"ADDR":"310 新竹縣竹東鎮雞林里大同路259號2樓"},{"SEQ":12,"ADDR":"310 新竹縣竹東鎮雞林里大同路259號3樓"},{"SEQ":13,"ADDR":"310 新竹縣竹東鎮雞林里大同路259號4樓"},{"SEQ":14,"ADDR":"310 新竹縣竹東鎮雞林里大同路259號5樓"},{"SEQ":15,"ADDR":"310 新竹縣竹東鎮雞林里大同路259號6樓"},{"SEQ":16,"ADDR":"310 新竹縣竹東鎮雞林里大同路261號2樓"},{"SEQ":17,"ADDR":"310 新竹縣竹東鎮雞林里大同路261號3樓"},{"SEQ":18,"ADDR":"310 新竹縣竹東鎮雞林里大同路261號4樓"},{"SEQ":19,"ADDR":"310 新竹縣竹東鎮雞林里大同路261號5樓"},{"SEQ":20,"ADDR":"310 新竹縣竹東鎮雞林里大同路261號6樓"},{"SEQ":21,"ADDR":"310 新竹縣竹東鎮雞林里大同路255-1號2樓"},{"SEQ":22,"ADDR":"310 新竹縣竹東鎮雞林里大同路255-1號3樓"},{"SEQ":23,"ADDR":"310 新竹縣竹東鎮雞林里大同路255-1號4樓"},{"SEQ":24,"ADDR":"310 新竹縣竹東鎮雞林里大同路255-1號5樓"},{"SEQ":25,"ADDR":"310 新竹縣竹東鎮雞林里大同路255-1號6樓"},{"SEQ":26,"ADDR":"310 新竹縣竹東鎮雞林里大同路255號2樓"},{"SEQ":27,"ADDR":"310 新竹縣竹東鎮雞林里大同路255號3樓"},{"SEQ":28,"ADDR":"310 新竹縣竹東鎮雞林里大同路255號4樓"},{"SEQ":29,"ADDR":"310 新竹縣竹東鎮雞林里大同路255號5樓"},{"SEQ":30,"ADDR":"310 新竹縣竹東鎮雞林里大同路255號6樓"}],"address":"310 新竹縣竹東鎮                林里大同路259-1號2樓","P01NAME":"山德開發有限公司 呂宏慶等 30 戶","LANCOUNT":3,"countyId":"I60"}]}


