

{"MSG":"搜尋到資料有1筆","count":1,"licenseData":[{"LANDATA":[{"LANDESC":"桃園縣大園鄉五塊厝段大埔小段540地號","SEQ":"1"},{"LANDESC":"桃園縣大園鄉五塊厝段大埔小段541地號","SEQ":"2"},{"LANDESC":"桃園縣大園鄉五塊厝段大埔小段542-3地號","SEQ":"3"}],"IMAGESTAT":"N","licenseStr_3":"(064)桃縣建都執照字第0156號","BUILDING_HEIGHT":"5.95Ｍ","BUILDING_NO":"幢 5棟 地上 2 層 地下  層 共 戶","ADRCOUNT":0,"licenseSeq":"06530024800990000I40","licenseStr_1":"(65)字第248號","issuedDate":"065/03/15","AREA_TOTAL":"騎樓：0㎡，其他：5062.5㎡","ADRDATA":"","address":" ","P01NAME":"華籐企業有限公司 張文慶","LANCOUNT":3,"countyId":"I40"}]}


