

{"MSG":"搜尋到資料有2筆","count":2,"licenseData":[{"LANDATA":[{"LANDESC":"臺南市安平區金華段42-26地號","SEQ":"1"}],"IMAGESTAT":"N","licenseStr_3":"(080)南工造字第76917號","BUILDING_HEIGHT":"16.8Ｍ","BUILDING_NO":"幢 1棟 地上 5 層 地下 0 層 共 1戶","ADRCOUNT":1,"licenseSeq":"08130078200000000IF0","licenseStr_1":"(81)南工字第782號","issuedDate":"081/11/23","AREA_TOTAL":"騎樓：0㎡，其他：113㎡","ADRDATA":[{"SEQ":1,"ADDR":" 建平八街372巷60號"}],"address":" 建平八街372巷60號","P01NAME":"郭秀邦","LANCOUNT":1,"countyId":"IF0"},{"LANDATA":[{"LANDESC":"臺南市北區光賢段223-4地號","SEQ":"1"}],"IMAGESTAT":"N","licenseStr_3":"(080)南工造字第75178號","BUILDING_HEIGHT":"13.4Ｍ","BUILDING_NO":"幢 1棟 地上 4 層 地下 0 層 共 1戶","ADRCOUNT":1,"licenseSeq":"08131078200010000IF0","licenseStr_1":"(81)南工字第110782號","issuedDate":"081/04/23","AREA_TOTAL":"騎樓：0㎡，其他：114.47㎡","ADRDATA":[{"SEQ":1,"ADDR":" 中華北路一段517巷49號"}],"address":" 中華北路一段517巷49號","P01NAME":"侯慶春","LANCOUNT":1,"countyId":"IF0"}]}


