

{"MSG":"搜尋到資料有3筆","count":3,"licenseData":[{"LANDATA":[{"LANDESC":"桃園縣楊梅市大平山下段106-21地號","SEQ":"1"},{"LANDESC":"桃園縣楊梅市大平山下段106-32地號","SEQ":"2"}],"IMAGESTAT":"N","licenseStr_3":"(74)桃縣建管執照字第01133號","BUILDING_HEIGHT":"7.6Ｍ","BUILDING_NO":"幢 1棟 地上 2 層 地下  層 共 1戶","ADRCOUNT":1,"licenseSeq":"0753H000200I40","licenseStr_1":"(75)桃縣建管使字第00002號","issuedDate":"075/01/14","AREA_TOTAL":"騎樓：0㎡，其他：94.72㎡","ADRDATA":[{"SEQ":1,"ADDR":"326 桃園縣楊梅市秀才路207巷120弄12號"}],"address":"326 桃園縣楊梅市秀才路207巷120弄12號","P01NAME":"溫九妹","LANCOUNT":2,"countyId":"I40"},{"LANDATA":[{"LANDESC":"桃園縣蘆竹鄉南崁廟口段廟口小段0145地號","SEQ":"1"},{"LANDESC":"桃園縣蘆竹鄉南崁廟口段廟口小段0145-0001地號","SEQ":"2"},{"LANDESC":"桃園縣蘆竹鄉南崁廟口段廟口小段0145-0002地號","SEQ":"3"},{"LANDESC":"桃園縣蘆竹鄉南崁廟口段廟口小段0145-0004地號","SEQ":"4"}],"IMAGESTAT":"N","licenseStr_3":"(73)桃縣建管執照字第工00742號","BUILDING_HEIGHT":"10.6Ｍ","BUILDING_NO":"幢 1棟 地上 4 層 地下 1 層 共 1戶","ADRCOUNT":1,"licenseSeq":"0753I000200I40","licenseStr_1":"(75)桃縣建管使工字第00002號","issuedDate":"075/01/04","AREA_TOTAL":"騎樓：49㎡，其他：3220㎡","ADRDATA":[{"SEQ":1,"ADDR":"338 桃園縣蘆竹鄉南山路1段113號"}],"address":"338 桃園縣蘆竹鄉南山路1段113號","P01NAME":"泰助企業股份有限公司 代：藍松江","LANCOUNT":4,"countyId":"I40"},{"LANDATA":[{"LANDESC":"桃園縣桃園市東門段0043地號","SEQ":"1"}],"IMAGESTAT":"N","licenseStr_3":"(74)桃縣建管執照字第其00101號","BUILDING_HEIGHT":"7.8Ｍ","BUILDING_NO":"幢 棟 地上 2 層 地下  層 共 戶","ADRCOUNT":1,"licenseSeq":"0753J000200I40","licenseStr_1":"(75)桃縣建管使其字第00002號","issuedDate":"075/01/08","AREA_TOTAL":"騎樓：0㎡，其他：245.53㎡","ADRDATA":[{"SEQ":1,"ADDR":"330 桃園縣桃園市成功路二段144號"}],"address":"330 桃園縣桃園市成功路二段144號","P01NAME":"台灣省管理機關台灣省立桃園高級農工職業學校  校長:唐山","LANCOUNT":1,"countyId":"I40"}]}


