

{"MSG":"搜尋到資料有2筆","count":2,"licenseData":[{"LANDATA":[{"LANDESC":"臺中市東區旱溪段32-3地號","SEQ":"1"},{"LANDESC":"臺中市東區旱溪段32-52地號","SEQ":"2"}],"IMAGESTAT":"N","licenseStr_3":"(062)中建都建字第1180號","BUILDING_HEIGHT":"9.3Ｍ","BUILDING_NO":"1幢 棟 地上 2 層 地下  層 共 戶","ADRCOUNT":2,"licenseSeq":"06330011400","licenseStr_1":"(63)中工建使字第114號","issuedDate":"063/02/15","AREA_TOTAL":"騎樓：0㎡，其他：208.32㎡","ADRDATA":[{"SEQ":1,"ADDR":"401 臺中市東區十甲東巷5號"},{"SEQ":2,"ADDR":"401 臺中市東區十甲東巷5號"}],"address":"401 臺中市東區十甲東巷5號","P01NAME":"永昌木器加工廠：林永木","LANCOUNT":2,"countyId":"I80"},{"LANDATA":[{"LANDESC":"臺中市大里區番子寮段175地號","SEQ":"1"},{"LANDESC":"臺中市大里區番子寮段174-7地號","SEQ":"2"}],"IMAGESTAT":"N","licenseStr_3":"63府都建使字第00114號","BUILDING_HEIGHT":"7Ｍ","BUILDING_NO":"幢 1棟 地上 2 層 地下  層 共 1戶","ADRCOUNT":1,"licenseSeq":"06330011400110000I90","licenseStr_1":"(63)建都營使字第00114號","issuedDate":"064/03/31","AREA_TOTAL":"騎樓：0㎡，其他：1469.5㎡","ADRDATA":[{"SEQ":1,"ADDR":"412 臺中市大里區善化路18號"}],"address":"412 臺中市大里區善化路18號","P01NAME":"","LANCOUNT":2,"countyId":"I90"}]}


