

{"MSG":"·j´M¨ì¸ê®Æ¦³1µ§","count":1,"licenseData":[{"LANDATA":[{"LANDESC":"®ç¶é¿¤Äª¦Ë¶m«n®r¤U¬q493¦a¸¹","SEQ":"1"}],"IMAGESTAT":"N","licenseStr_3":"(89)®ç¿¤¤u«Ø°õ·Ó¦r²Ä·|Äª00371¸¹","BUILDING_HEIGHT":"39.15¢Û","BUILDING_NO":"¼l 2´É ¦a¤W 12 ¼h ¦a¤U 2 ¼h ¦@ 172¤á","ADRCOUNT":172,"licenseSeq":"09230002400I40","licenseStr_1":"(92)®ç¿¤¤u«Ø¨Ï¦r²ÄÄª00024¸¹","issuedDate":"092/01/09","AREA_TOTAL":"ÃM¼Ó¡G236.32¢T¡A¨ä¥L¡G4506.68¢T","ADRDATA":[{"SEQ":1,"ADDR":"338 ®ç¶é¿¤Äª¦Ë¶m«n¿³§ø4¾F©^¤Æ¸ô40¸¹"},{"SEQ":2,"ADDR":"338 ®ç¶é¿¤Äª¦Ë¶m«n¿³§ø4¾F©^¤Æ¸ô42¸¹"},{"SEQ":3,"ADDR":"338 ®ç¶é¿¤Äª¦Ë¶m«n¿³§ø4¾F©^¤Æ¸ô46¸¹"},{"SEQ":4,"ADDR":"338 ®ç¶é¿¤Äª¦Ë¶m«n¿³§ø4¾F©^¤Æ¸ô48¸¹"},{"SEQ":5,"ADDR":"338 ®ç¶é¿¤Äª¦Ë¶m«n¿³§ø4¾F©^¤Æ¸ô50¸¹"},{"SEQ":6,"ADDR":"338 ®ç¶é¿¤Äª¦Ë¶m«n¿³§ø4¾F©^¤Æ¸ô52¸¹"},{"SEQ":7,"ADDR":"338 ®ç¶é¿¤Äª¦Ë¶m«n¿³§ø4¾F©^¤Æ¸ô54¸¹"},{"SEQ":8,"ADDR":"338 ®ç¶é¿¤Äª¦Ë¶m«n¿³§ø4¾F©^¤Æ¸ô54¸¹¤§1"},{"SEQ":9,"ADDR":"338 ®ç¶é¿¤Äª¦Ë¶m«n¿³§ø4¾F©^¤Æ¸ô54¸¹¤§2"},{"SEQ":10,"ADDR":"338 ®ç¶é¿¤Äª¦Ë¶m«n¿³§ø4¾F©^¤Æ¸ô54¸¹¤§3"},{"SEQ":11,"ADDR":"338 ®ç¶é¿¤Äª¦Ë¶m«n¿³§ø4¾F©^¤Æ¸ô54¸¹¤§5"},{"SEQ":12,"ADDR":"338 ®ç¶é¿¤Äª¦Ë¶m«n¿³§ø4¾F©^¤Æ¸ô54¸¹¤§6"},{"SEQ":13,"ADDR":"338 ®ç¶é¿¤Äª¦Ë¶m«n¿³§ø4¾F«n¶¶¤@µó6¸¹"},{"SEQ":14,"ADDR":"338 ®ç¶é¿¤Äª¦Ë¶m«n¿³§ø4¾F«n¶¶¤@µó6¸¹2¼Ó"},{"SEQ":15,"ADDR":"338 ®ç¶é¿¤Äª¦Ë¶m«n¿³§ø4¾F«n¶¶¤@µó6¸¹3¼Ó"},{"SEQ":16,"ADDR":"338 ®ç¶é¿¤Äª¦Ë¶m«n¿³§ø4¾F«n¶¶¤@µó6¸¹4¼Ó"},{"SEQ":17,"ADDR":"338 ®ç¶é¿¤Äª¦Ë¶m«n¿³§ø4¾F«n¶¶¤@µó6¸¹5¼Ó"},{"SEQ":18,"ADDR":"338 ®ç¶é¿¤Äª¦Ë¶m«n¿³§ø4¾F«n¶¶¤@µó6¸¹6¼Ó"},{"SEQ":19,"ADDR":"338 ®ç¶é¿¤Äª¦Ë¶m«n¿³§ø4¾F«n¶¶¤@µó6¸¹7¼Ó"},{"SEQ":20,"ADDR":"338 ®ç¶é¿¤Äª¦Ë¶m«n¿³§ø4¾F«n¶¶¤@µó6¸¹8¼Ó"},{"SEQ":21,"ADDR":"338 ®ç¶é¿¤Äª¦Ë¶m«n¿³§ø4¾F«n¶¶¤@µó6¸¹9¼Ó"},{"SEQ":22,"ADDR":"338 ®ç¶é¿¤Äª¦Ë¶m«n¿³§ø4¾F«n¶¶¤@µó6¸¹10¼Ó"},{"SEQ":23,"ADDR":"338 ®ç¶é¿¤Äª¦Ë¶m«n¿³§ø4¾F«n¶¶¤@µó6¸¹11¼Ó"},{"SEQ":24,"ADDR":"338 ®ç¶é¿¤Äª¦Ë¶m«n¿³§ø4¾F«n¶¶¤@µó6¸¹12¼Ó"},{"SEQ":25,"ADDR":"338 ®ç¶é¿¤Äª¦Ë¶m«n¿³§ø4¾F«n¶¶¤@µó8¸¹3¼Ó"},{"SEQ":26,"ADDR":"338 ®ç¶é¿¤Äª¦Ë¶m«n¿³§ø4¾F«n¶¶¤@µó8¸¹4¼Ó"},{"SEQ":27,"ADDR":"338 ®ç¶é¿¤Äª¦Ë¶m«n¿³§ø4¾F«n¶¶¤@µó8¸¹5¼Ó"},{"SEQ":28,"ADDR":"338 ®ç¶é¿¤Äª¦Ë¶m«n¿³§ø4¾F«n¶¶¤@µó8¸¹6¼Ó"},{"SEQ":29,"ADDR":"338 ®ç¶é¿¤Äª¦Ë¶m«n¿³§ø4¾F«n¶¶¤@µó8¸¹7¼Ó"},{"SEQ":30,"ADDR":"338 ®ç¶é¿¤Äª¦Ë¶m«n¿³§ø4¾F«n¶¶¤@µó8¸¹8¼Ó"},{"SEQ":31,"ADDR":"338 ®ç¶é¿¤Äª¦Ë¶m«n¿³§ø4¾F«n¶¶¤@µó8¸¹9¼Ó"},{"SEQ":32,"ADDR":"338 ®ç¶é¿¤Äª¦Ë¶m«n¿³§ø4¾F«n¶¶¤@µó8¸¹10¼Ó"},{"SEQ":33,"ADDR":"338 ®ç¶é¿¤Äª¦Ë¶m«n¿³§ø4¾F«n¶¶¤@µó8¸¹11¼Ó"},{"SEQ":34,"ADDR":"338 ®ç¶é¿¤Äª¦Ë¶m«n¿³§ø4¾F«n¶¶¤@µó8¸¹12¼Ó"},{"SEQ":35,"ADDR":"338 ®ç¶é¿¤Äª¦Ë¶m«n¿³§ø4¾F«n¶¶¤@µó10¸¹"},{"SEQ":36,"ADDR":"338 ®ç¶é¿¤Äª¦Ë¶m«n¿³§ø4¾F«n¶¶¤@µó10¸¹3¼Ó"},{"SEQ":37,"ADDR":"338 ®ç¶é¿¤Äª¦Ë¶m«n¿³§ø4¾F«n¶¶¤@µó10¸¹4¼Ó"},{"SEQ":38,"ADDR":"338 ®ç¶é¿¤Äª¦Ë¶m«n¿³§ø4¾F«n¶¶¤@µó10¸¹5¼Ó"},{"SEQ":39,"ADDR":"338 ®ç¶é¿¤Äª¦Ë¶m«n¿³§ø4¾F«n¶¶¤@µó10¸¹6¼Ó"},{"SEQ":40,"ADDR":"338 ®ç¶é¿¤Äª¦Ë¶m«n¿³§ø4¾F«n¶¶¤@µó10¸¹7¼Ó"},{"SEQ":41,"ADDR":"338 ®ç¶é¿¤Äª¦Ë¶m«n¿³§ø4¾F«n¶¶¤@µó10¸¹8¼Ó"},{"SEQ":42,"ADDR":"338 ®ç¶é¿¤Äª¦Ë¶m«n¿³§ø4¾F«n¶¶¤@µó10¸¹9¼Ó"},{"SEQ":43,"ADDR":"338 ®ç¶é¿¤Äª¦Ë¶m«n¿³§ø4¾F«n¶¶¤@µó10¸¹10¼Ó"},{"SEQ":44,"ADDR":"338 ®ç¶é¿¤Äª¦Ë¶m«n¿³§ø4¾F«n¶¶¤@µó10¸¹11¼Ó"},{"SEQ":45,"ADDR":"338 ®ç¶é¿¤Äª¦Ë¶m«n¿³§ø4¾F«n¶¶¤@µó10¸¹12¼Ó"},{"SEQ":46,"ADDR":"338 ®ç¶é¿¤Äª¦Ë¶m«n¿³§ø4¾F«n¶¶¤@µó12¸¹"},{"SEQ":47,"ADDR":"338 ®ç¶é¿¤Äª¦Ë¶m«n¿³§ø4¾F«n¶¶¤@µó12¸¹2¼Ó"},{"SEQ":48,"ADDR":"338 ®ç¶é¿¤Äª¦Ë¶m«n¿³§ø4¾F«n¶¶¤@µó12¸¹3¼Ó"},{"SEQ":49,"ADDR":"338 ®ç¶é¿¤Äª¦Ë¶m«n¿³§ø4¾F«n¶¶¤@µó12¸¹4¼Ó"},{"SEQ":50,"ADDR":"338 ®ç¶é¿¤Äª¦Ë¶m«n¿³§ø4¾F«n¶¶¤@µó12¸¹5¼Ó"},{"SEQ":51,"ADDR":"338 ®ç¶é¿¤Äª¦Ë¶m«n¿³§ø4¾F«n¶¶¤@µó12¸¹6¼Ó"},{"SEQ":52,"ADDR":"338 ®ç¶é¿¤Äª¦Ë¶m«n¿³§ø4¾F«n¶¶¤@µó12¸¹7¼Ó"},{"SEQ":53,"ADDR":"338 ®ç¶é¿¤Äª¦Ë¶m«n¿³§ø4¾F«n¶¶¤@µó12¸¹8¼Ó"},{"SEQ":54,"ADDR":"338 ®ç¶é¿¤Äª¦Ë¶m«n¿³§ø4¾F«n¶¶¤@µó12¸¹9¼Ó"},{"SEQ":55,"ADDR":"338 ®ç¶é¿¤Äª¦Ë¶m«n¿³§ø4¾F«n¶¶¤@µó12¸¹10¼Ó"},{"SEQ":56,"ADDR":"338 ®ç¶é¿¤Äª¦Ë¶m«n¿³§ø4¾F«n¶¶¤@µó12¸¹11¼Ó"},{"SEQ":57,"ADDR":"338 ®ç¶é¿¤Äª¦Ë¶m«n¿³§ø4¾F«n¶¶¤@µó12¸¹12¼Ó"},{"SEQ":58,"ADDR":"338 ®ç¶é¿¤Äª¦Ë¶m«n¿³§ø4¾F«n¶¶¤@µó14¸¹2¼Ó"},{"SEQ":59,"ADDR":"338 ®ç¶é¿¤Äª¦Ë¶m«n¿³§ø4¾F«n¶¶¤@µó14¸¹3¼Ó"},{"SEQ":60,"ADDR":"338 ®ç¶é¿¤Äª¦Ë¶m«n¿³§ø4¾F«n¶¶¤@µó14¸¹4¼Ó"},{"SEQ":61,"ADDR":"338 ®ç¶é¿¤Äª¦Ë¶m«n¿³§ø4¾F«n¶¶¤@µó14¸¹5¼Ó"},{"SEQ":62,"ADDR":"338 ®ç¶é¿¤Äª¦Ë¶m«n¿³§ø4¾F«n¶¶¤@µó14¸¹6¼Ó"},{"SEQ":63,"ADDR":"338 ®ç¶é¿¤Äª¦Ë¶m«n¿³§ø4¾F«n¶¶¤@µó14¸¹7¼Ó"},{"SEQ":64,"ADDR":"338 ®ç¶é¿¤Äª¦Ë¶m«n¿³§ø4¾F«n¶¶¤@µó14¸¹8¼Ó"},{"SEQ":65,"ADDR":"338 ®ç¶é¿¤Äª¦Ë¶m«n¿³§ø4¾F«n¶¶¤@µó14¸¹9¼Ó"},{"SEQ":66,"ADDR":"338 ®ç¶é¿¤Äª¦Ë¶m«n¿³§ø4¾F«n¶¶¤@µó14¸¹10¼Ó"},{"SEQ":67,"ADDR":"338 ®ç¶é¿¤Äª¦Ë¶m«n¿³§ø4¾F«n¶¶¤@µó14¸¹11¼Ó"},{"SEQ":68,"ADDR":"338 ®ç¶é¿¤Äª¦Ë¶m«n¿³§ø4¾F«n¶¶¤@µó14¸¹12¼Ó"},{"SEQ":69,"ADDR":"338 ®ç¶é¿¤Äª¦Ë¶m«n¿³§ø4¾F«n¶¶¤@µó16¸¹"},{"SEQ":70,"ADDR":"338 ®ç¶é¿¤Äª¦Ë¶m«n¿³§ø4¾F«n¶¶¤@µó16¸¹2¼Ó"},{"SEQ":71,"ADDR":"338 ®ç¶é¿¤Äª¦Ë¶m«n¿³§ø4¾F«n¶¶¤@µó16¸¹3¼Ó"},{"SEQ":72,"ADDR":"338 ®ç¶é¿¤Äª¦Ë¶m«n¿³§ø4¾F«n¶¶¤@µó16¸¹4¼Ó"},{"SEQ":73,"ADDR":"338 ®ç¶é¿¤Äª¦Ë¶m«n¿³§ø4¾F«n¶¶¤@µó16¸¹5¼Ó"},{"SEQ":74,"ADDR":"338 ®ç¶é¿¤Äª¦Ë¶m«n¿³§ø4¾F«n¶¶¤@µó16¸¹6¼Ó"},{"SEQ":75,"ADDR":"338 ®ç¶é¿¤Äª¦Ë¶m«n¿³§ø4¾F«n¶¶¤@µó16¸¹7¼Ó"},{"SEQ":76,"ADDR":"338 ®ç¶é¿¤Äª¦Ë¶m«n¿³§ø4¾F«n¶¶¤@µó16¸¹8¼Ó"},{"SEQ":77,"ADDR":"338 ®ç¶é¿¤Äª¦Ë¶m«n¿³§ø4¾F«n¶¶¤@µó16¸¹9¼Ó"},{"SEQ":78,"ADDR":"338 ®ç¶é¿¤Äª¦Ë¶m«n¿³§ø4¾F«n¶¶¤@µó16¸¹10¼Ó"},{"SEQ":79,"ADDR":"338 ®ç¶é¿¤Äª¦Ë¶m«n¿³§ø4¾F«n¶¶¤@µó16¸¹11¼Ó"},{"SEQ":80,"ADDR":"338 ®ç¶é¿¤Äª¦Ë¶m«n¿³§ø4¾F«n¶¶¤@µó16¸¹12¼Ó"},{"SEQ":81,"ADDR":"338 ®ç¶é¿¤Äª¦Ë¶m«n¿³§ø4¾F«n¶¶¤@µó18¸¹3¼Ó"},{"SEQ":82,"ADDR":"338 ®ç¶é¿¤Äª¦Ë¶m«n¿³§ø4¾F«n¶¶¤@µó18¸¹4¼Ó"},{"SEQ":83,"ADDR":"338 ®ç¶é¿¤Äª¦Ë¶m«n¿³§ø4¾F«n¶¶¤@µó18¸¹5¼Ó"},{"SEQ":84,"ADDR":"338 ®ç¶é¿¤Äª¦Ë¶m«n¿³§ø4¾F«n¶¶¤@µó18¸¹6¼Ó"},{"SEQ":85,"ADDR":"338 ®ç¶é¿¤Äª¦Ë¶m«n¿³§ø4¾F«n¶¶¤@µó18¸¹7¼Ó"},{"SEQ":86,"ADDR":"338 ®ç¶é¿¤Äª¦Ë¶m«n¿³§ø4¾F«n¶¶¤@µó18¸¹8¼Ó"},{"SEQ":87,"ADDR":"338 ®ç¶é¿¤Äª¦Ë¶m«n¿³§ø4¾F«n¶¶¤@µó18¸¹9¼Ó"},{"SEQ":88,"ADDR":"338 ®ç¶é¿¤Äª¦Ë¶m«n¿³§ø4¾F«n¶¶¤@µó18¸¹10¼Ó"},{"SEQ":89,"ADDR":"338 ®ç¶é¿¤Äª¦Ë¶m«n¿³§ø4¾F«n¶¶¤@µó18¸¹11¼Ó"},{"SEQ":90,"ADDR":"338 ®ç¶é¿¤Äª¦Ë¶m«n¿³§ø4¾F«n¶¶¤@µó18¸¹12¼Ó"},{"SEQ":91,"ADDR":"338 ®ç¶é¿¤Äª¦Ë¶m«n¿³§ø4¾F«n¶¶¤@µó20¸¹3¼Ó"},{"SEQ":92,"ADDR":"338 ®ç¶é¿¤Äª¦Ë¶m«n¿³§ø4¾F«n¶¶¤@µó20¸¹4¼Ó"},{"SEQ":93,"ADDR":"338 ®ç¶é¿¤Äª¦Ë¶m«n¿³§ø4¾F«n¶¶¤@µó20¸¹5¼Ó"},{"SEQ":94,"ADDR":"338 ®ç¶é¿¤Äª¦Ë¶m«n¿³§ø4¾F«n¶¶¤@µó20¸¹6¼Ó"},{"SEQ":95,"ADDR":"338 ®ç¶é¿¤Äª¦Ë¶m«n¿³§ø4¾F«n¶¶¤@µó20¸¹7¼Ó"},{"SEQ":96,"ADDR":"338 ®ç¶é¿¤Äª¦Ë¶m«n¿³§ø4¾F«n¶¶¤@µó20¸¹8¼Ó"},{"SEQ":97,"ADDR":"338 ®ç¶é¿¤Äª¦Ë¶m«n¿³§ø4¾F«n¶¶¤@µó20¸¹9¼Ó"},{"SEQ":98,"ADDR":"338 ®ç¶é¿¤Äª¦Ë¶m«n¿³§ø4¾F«n¶¶¤@µó20¸¹10¼Ó"},{"SEQ":99,"ADDR":"338 ®ç¶é¿¤Äª¦Ë¶m«n¿³§ø4¾F«n¶¶¤@µó20¸¹11¼Ó"},{"SEQ":100,"ADDR":"338 ®ç¶é¿¤Äª¦Ë¶m«n¿³§ø4¾F«n¶¶¤@µó20¸¹12¼Ó"},{"SEQ":101,"ADDR":"338 ®ç¶é¿¤Äª¦Ë¶m«n¿³§ø4¾F«n¶¶¤@µó22¸¹"},{"SEQ":102,"ADDR":"338 ®ç¶é¿¤Äª¦Ë¶m«n¿³§ø4¾F«n¶¶¤@µó22¸¹2¼Ó"},{"SEQ":103,"ADDR":"338 ®ç¶é¿¤Äª¦Ë¶m«n¿³§ø4¾F«n¶¶¤@µó22¸¹3¼Ó"},{"SEQ":104,"ADDR":"338 ®ç¶é¿¤Äª¦Ë¶m«n¿³§ø4¾F«n¶¶¤@µó22¸¹4¼Ó"},{"SEQ":105,"ADDR":"338 ®ç¶é¿¤Äª¦Ë¶m«n¿³§ø4¾F«n¶¶¤@µó22¸¹5¼Ó"},{"SEQ":106,"ADDR":"338 ®ç¶é¿¤Äª¦Ë¶m«n¿³§ø4¾F«n¶¶¤@µó22¸¹6¼Ó"},{"SEQ":107,"ADDR":"338 ®ç¶é¿¤Äª¦Ë¶m«n¿³§ø4¾F«n¶¶¤@µó22¸¹7¼Ó"},{"SEQ":108,"ADDR":"338 ®ç¶é¿¤Äª¦Ë¶m«n¿³§ø4¾F«n¶¶¤@µó22¸¹8¼Ó"},{"SEQ":109,"ADDR":"338 ®ç¶é¿¤Äª¦Ë¶m«n¿³§ø4¾F«n¶¶¤@µó22¸¹9¼Ó"},{"SEQ":110,"ADDR":"338 ®ç¶é¿¤Äª¦Ë¶m«n¿³§ø4¾F«n¶¶¤@µó22¸¹10¼Ó"},{"SEQ":111,"ADDR":"338 ®ç¶é¿¤Äª¦Ë¶m«n¿³§ø4¾F«n¶¶¤@µó22¸¹11¼Ó"},{"SEQ":112,"ADDR":"338 ®ç¶é¿¤Äª¦Ë¶m«n¿³§ø4¾F«n¶¶¤@µó22¸¹12¼Ó"},{"SEQ":113,"ADDR":"338 ®ç¶é¿¤Äª¦Ë¶m«n¿³§ø4¾F«n¶¶¤@µó24¸¹"},{"SEQ":114,"ADDR":"338 ®ç¶é¿¤Äª¦Ë¶m«n¿³§ø4¾F«n¶¶¤@µó24¸¹2¼Ó"},{"SEQ":115,"ADDR":"338 ®ç¶é¿¤Äª¦Ë¶m«n¿³§ø4¾F«n¶¶¤@µó24¸¹3¼Ó"},{"SEQ":116,"ADDR":"338 ®ç¶é¿¤Äª¦Ë¶m«n¿³§ø4¾F«n¶¶¤@µó24¸¹4¼Ó"},{"SEQ":117,"ADDR":"338 ®ç¶é¿¤Äª¦Ë¶m«n¿³§ø4¾F«n¶¶¤@µó24¸¹5¼Ó"},{"SEQ":118,"ADDR":"338 ®ç¶é¿¤Äª¦Ë¶m«n¿³§ø4¾F«n¶¶¤@µó24¸¹6¼Ó"},{"SEQ":119,"ADDR":"338 ®ç¶é¿¤Äª¦Ë¶m«n¿³§ø4¾F«n¶¶¤@µó24¸¹7¼Ó"},{"SEQ":120,"ADDR":"338 ®ç¶é¿¤Äª¦Ë¶m«n¿³§ø4¾F«n¶¶¤@µó24¸¹8¼Ó"},{"SEQ":121,"ADDR":"338 ®ç¶é¿¤Äª¦Ë¶m«n¿³§ø4¾F«n¶¶¤@µó24¸¹9¼Ó"},{"SEQ":122,"ADDR":"338 ®ç¶é¿¤Äª¦Ë¶m«n¿³§ø4¾F«n¶¶¤@µó24¸¹10¼Ó"},{"SEQ":123,"ADDR":"338 ®ç¶é¿¤Äª¦Ë¶m«n¿³§ø4¾F«n¶¶¤@µó24¸¹11¼Ó"},{"SEQ":124,"ADDR":"338 ®ç¶é¿¤Äª¦Ë¶m«n¿³§ø4¾F«n¶¶¤@µó24¸¹12¼Ó"},{"SEQ":125,"ADDR":"338 ®ç¶é¿¤Äª¦Ë¶m«n¿³§ø4¾F«n¶¶¤@µó26¸¹"},{"SEQ":126,"ADDR":"338 ®ç¶é¿¤Äª¦Ë¶m«n¿³§ø4¾F«n¶¶¤@µó26¸¹2¼Ó"},{"SEQ":127,"ADDR":"338 ®ç¶é¿¤Äª¦Ë¶m«n¿³§ø4¾F«n¶¶¤@µó26¸¹3¼Ó"},{"SEQ":128,"ADDR":"338 ®ç¶é¿¤Äª¦Ë¶m«n¿³§ø4¾F«n¶¶¤@µó26¸¹4¼Ó"},{"SEQ":129,"ADDR":"338 ®ç¶é¿¤Äª¦Ë¶m«n¿³§ø4¾F«n¶¶¤@µó26¸¹5¼Ó"},{"SEQ":130,"ADDR":"338 ®ç¶é¿¤Äª¦Ë¶m«n¿³§ø4¾F«n¶¶¤@µó26¸¹6¼Ó"},{"SEQ":131,"ADDR":"338 ®ç¶é¿¤Äª¦Ë¶m«n¿³§ø4¾F«n¶¶¤@µó26¸¹7¼Ó"},{"SEQ":132,"ADDR":"338 ®ç¶é¿¤Äª¦Ë¶m«n¿³§ø4¾F«n¶¶¤@µó26¸¹8¼Ó"},{"SEQ":133,"ADDR":"338 ®ç¶é¿¤Äª¦Ë¶m«n¿³§ø4¾F«n¶¶¤@µó26¸¹9¼Ó"},{"SEQ":134,"ADDR":"338 ®ç¶é¿¤Äª¦Ë¶m«n¿³§ø4¾F«n¶¶¤@µó26¸¹10¼Ó"},{"SEQ":135,"ADDR":"338 ®ç¶é¿¤Äª¦Ë¶m«n¿³§ø4¾F«n¶¶¤@µó26¸¹11¼Ó"},{"SEQ":136,"ADDR":"338 ®ç¶é¿¤Äª¦Ë¶m«n¿³§ø4¾F«n¶¶¤@µó26¸¹12¼Ó"},{"SEQ":137,"ADDR":"338 ®ç¶é¿¤Äª¦Ë¶m«n¿³§ø4¾F«n¶¶¤@µó28¸¹"},{"SEQ":138,"ADDR":"338 ®ç¶é¿¤Äª¦Ë¶m«n¿³§ø4¾F«n¶¶¤@µó28¸¹2¼Ó"},{"SEQ":139,"ADDR":"338 ®ç¶é¿¤Äª¦Ë¶m«n¿³§ø4¾F«n¶¶¤@µó28¸¹3¼Ó"},{"SEQ":140,"ADDR":"338 ®ç¶é¿¤Äª¦Ë¶m«n¿³§ø4¾F«n¶¶¤@µó28¸¹4¼Ó"},{"SEQ":141,"ADDR":"338 ®ç¶é¿¤Äª¦Ë¶m«n¿³§ø4¾F«n¶¶¤@µó28¸¹5¼Ó"},{"SEQ":142,"ADDR":"338 ®ç¶é¿¤Äª¦Ë¶m«n¿³§ø4¾F«n¶¶¤@µó28¸¹6¼Ó"},{"SEQ":143,"ADDR":"338 ®ç¶é¿¤Äª¦Ë¶m«n¿³§ø4¾F«n¶¶¤@µó28¸¹7¼Ó"},{"SEQ":144,"ADDR":"338 ®ç¶é¿¤Äª¦Ë¶m«n¿³§ø4¾F«n¶¶¤@µó28¸¹8¼Ó"},{"SEQ":145,"ADDR":"338 ®ç¶é¿¤Äª¦Ë¶m«n¿³§ø4¾F«n¶¶¤@µó28¸¹9¼Ó"},{"SEQ":146,"ADDR":"338 ®ç¶é¿¤Äª¦Ë¶m«n¿³§ø4¾F«n¶¶¤@µó28¸¹10¼Ó"},{"SEQ":147,"ADDR":"338 ®ç¶é¿¤Äª¦Ë¶m«n¿³§ø4¾F«n¶¶¤@µó28¸¹11¼Ó"},{"SEQ":148,"ADDR":"338 ®ç¶é¿¤Äª¦Ë¶m«n¿³§ø4¾F«n¶¶¤@µó28¸¹12¼Ó"},{"SEQ":149,"ADDR":"338 ®ç¶é¿¤Äª¦Ë¶m«n¿³§ø4¾F«n¶¶¤@µó30¸¹"},{"SEQ":150,"ADDR":"338 ®ç¶é¿¤Äª¦Ë¶m«n¿³§ø4¾F«n¶¶¤@µó30¸¹2¼Ó"},{"SEQ":151,"ADDR":"338 ®ç¶é¿¤Äª¦Ë¶m«n¿³§ø4¾F«n¶¶¤@µó30¸¹3¼Ó"},{"SEQ":152,"ADDR":"338 ®ç¶é¿¤Äª¦Ë¶m«n¿³§ø4¾F«n¶¶¤@µó30¸¹4¼Ó"},{"SEQ":153,"ADDR":"338 ®ç¶é¿¤Äª¦Ë¶m«n¿³§ø4¾F«n¶¶¤@µó30¸¹5¼Ó"},{"SEQ":154,"ADDR":"338 ®ç¶é¿¤Äª¦Ë¶m«n¿³§ø4¾F«n¶¶¤@µó30¸¹6¼Ó"},{"SEQ":155,"ADDR":"338 ®ç¶é¿¤Äª¦Ë¶m«n¿³§ø4¾F«n¶¶¤@µó30¸¹7¼Ó"},{"SEQ":156,"ADDR":"338 ®ç¶é¿¤Äª¦Ë¶m«n¿³§ø4¾F«n¶¶¤@µó30¸¹8¼Ó"},{"SEQ":157,"ADDR":"338 ®ç¶é¿¤Äª¦Ë¶m«n¿³§ø4¾F«n¶¶¤@µó30¸¹9¼Ó"},{"SEQ":158,"ADDR":"338 ®ç¶é¿¤Äª¦Ë¶m«n¿³§ø4¾F«n¶¶¤@µó30¸¹10¼Ó"},{"SEQ":159,"ADDR":"338 ®ç¶é¿¤Äª¦Ë¶m«n¿³§ø4¾F«n¶¶¤@µó30¸¹11¼Ó"},{"SEQ":160,"ADDR":"338 ®ç¶é¿¤Äª¦Ë¶m«n¿³§ø4¾F«n¶¶¤@µó30¸¹12¼Ó"},{"SEQ":161,"ADDR":"338 ®ç¶é¿¤Äª¦Ë¶m«n¿³§ø4¾F«n¶¶¤@µó32¸¹"},{"SEQ":162,"ADDR":"338 ®ç¶é¿¤Äª¦Ë¶m«n¿³§ø4¾F«n¶¶¤@µó32¸¹2¼Ó"},{"SEQ":163,"ADDR":"338 ®ç¶é¿¤Äª¦Ë¶m«n¿³§ø4¾F«n¶¶¤@µó32¸¹3¼Ó"},{"SEQ":164,"ADDR":"338 ®ç¶é¿¤Äª¦Ë¶m«n¿³§ø4¾F«n¶¶¤@µó32¸¹4¼Ó"},{"SEQ":165,"ADDR":"338 ®ç¶é¿¤Äª¦Ë¶m«n¿³§ø4¾F«n¶¶¤@µó32¸¹5¼Ó"},{"SEQ":166,"ADDR":"338 ®ç¶é¿¤Äª¦Ë¶m«n¿³§ø4¾F«n¶¶¤@µó32¸¹6¼Ó"},{"SEQ":167,"ADDR":"338 ®ç¶é¿¤Äª¦Ë¶m«n¿³§ø4¾F«n¶¶¤@µó32¸¹7¼Ó"},{"SEQ":168,"ADDR":"338 ®ç¶é¿¤Äª¦Ë¶m«n¿³§ø4¾F«n¶¶¤@µó32¸¹8¼Ó"},{"SEQ":169,"ADDR":"338 ®ç¶é¿¤Äª¦Ë¶m«n¿³§ø4¾F«n¶¶¤@µó32¸¹9¼Ó"},{"SEQ":170,"ADDR":"338 ®ç¶é¿¤Äª¦Ë¶m«n¿³§ø4¾F«n¶¶¤@µó32¸¹10¼Ó"},{"SEQ":171,"ADDR":"338 ®ç¶é¿¤Äª¦Ë¶m«n¿³§ø4¾F«n¶¶¤@µó32¸¹11¼Ó"},{"SEQ":172,"ADDR":"338 ®ç¶é¿¤Äª¦Ë¶m«n¿³§ø4¾F«n¶¶¤@µó32¸¹12¼Ó"}],"address":"338 ®ç¶é¿¤Äª¦Ë¶m«n¿³§ø4¾F©^¤Æ¸ô40¸¹","P01NAME":"","LANCOUNT":1,"countyId":"I40"}]}


