

{"MSG":"搜尋到資料有31筆","count":31,"licenseData":[{"LANDATA":[{"LANDESC":"桃園縣桃園市埔子段埔子小段1735-3地號","SEQ":"1"},{"LANDESC":"桃園縣桃園市埔子段埔子小段1743地號","SEQ":"2"},{"LANDESC":"桃園縣桃園市埔子段埔子小段1735地號","SEQ":"3"}],"IMAGESTAT":"N","licenseStr_3":"(061)建都字第71號","BUILDING_HEIGHT":"","BUILDING_NO":"幢 棟 地上  層 地下  層 共 戶","ADRCOUNT":1,"licenseSeq":"06130056600400000I40","licenseStr_1":"(61)桃縣建都使字第566號","issuedDate":"","AREA_TOTAL":"騎樓：14.7㎡，其他：53.69㎡","ADRDATA":[{"SEQ":1,"ADDR":"330 桃園縣桃園市東埔里"}],"address":"330 桃園縣桃園市東埔里","P01NAME":"蔡寶猜","LANCOUNT":3,"countyId":"I40"},{"LANDATA":[{"LANDESC":"桃園縣桃園市埔子段埔子小段1735-3地號","SEQ":"1"},{"LANDESC":"桃園縣桃園市埔子段埔子小段1743地號","SEQ":"2"},{"LANDESC":"桃園縣桃園市埔子段埔子小段1735地號","SEQ":"3"}],"IMAGESTAT":"N","licenseStr_3":"(061)建都字第71號","BUILDING_HEIGHT":"","BUILDING_NO":"幢 棟 地上  層 地下  層 共 戶","ADRCOUNT":1,"licenseSeq":"06130056600400010I40","licenseStr_1":"(61)桃縣建都使字第566-1號","issuedDate":"","AREA_TOTAL":"騎樓：14.7㎡，其他：56.11㎡","ADRDATA":[{"SEQ":1,"ADDR":"330 桃園縣桃園市東埔里"}],"address":"330 桃園縣桃園市東埔里","P01NAME":"陳呂菊英","LANCOUNT":3,"countyId":"I40"},{"LANDATA":[{"LANDESC":"桃園縣桃園市埔子段埔子小段1735-3地號","SEQ":"1"},{"LANDESC":"桃園縣桃園市埔子段埔子小段1743地號","SEQ":"2"},{"LANDESC":"桃園縣桃園市埔子段埔子小段1735地號","SEQ":"3"}],"IMAGESTAT":"N","licenseStr_3":"(061)建都字第71號","BUILDING_HEIGHT":"","BUILDING_NO":"幢 棟 地上  層 地下  層 共 戶","ADRCOUNT":1,"licenseSeq":"06130056600400020I40","licenseStr_1":"(61)桃縣建都使字第566-2號","issuedDate":"","AREA_TOTAL":"騎樓：14.7㎡，其他：58.05㎡","ADRDATA":[{"SEQ":1,"ADDR":"330 桃園縣桃園市東埔里"}],"address":"330 桃園縣桃園市東埔里","P01NAME":"張魏彩娥","LANCOUNT":3,"countyId":"I40"},{"LANDATA":[{"LANDESC":"桃園縣桃園市埔子段埔子小段1735-3地號","SEQ":"1"},{"LANDESC":"桃園縣桃園市埔子段埔子小段1743地號","SEQ":"2"},{"LANDESC":"桃園縣桃園市埔子段埔子小段1735地號","SEQ":"3"}],"IMAGESTAT":"N","licenseStr_3":"(061)建都字第71號","BUILDING_HEIGHT":"","BUILDING_NO":"幢 棟 地上  層 地下  層 共 戶","ADRCOUNT":1,"licenseSeq":"06130056600400030I40","licenseStr_1":"(61)桃縣建都使字第566-3號","issuedDate":"","AREA_TOTAL":"騎樓：14.7㎡，其他：59.99㎡","ADRDATA":[{"SEQ":1,"ADDR":"330 桃園縣桃園市東埔里"}],"address":"330 桃園縣桃園市東埔里","P01NAME":"邱童杏","LANCOUNT":3,"countyId":"I40"},{"LANDATA":[{"LANDESC":"桃園縣桃園市埔子段埔子小段1735-3地號","SEQ":"1"},{"LANDESC":"桃園縣桃園市埔子段埔子小段1743地號","SEQ":"2"},{"LANDESC":"桃園縣桃園市埔子段埔子小段1735地號","SEQ":"3"}],"IMAGESTAT":"N","licenseStr_3":"(061)建都字第71號","BUILDING_HEIGHT":"","BUILDING_NO":"幢 棟 地上  層 地下  層 共 戶","ADRCOUNT":1,"licenseSeq":"06130056600400040I40","licenseStr_1":"(61)桃縣建都使字第566-4號","issuedDate":"","AREA_TOTAL":"騎樓：14.7㎡，其他：61.93㎡","ADRDATA":[{"SEQ":1,"ADDR":"330 桃園縣桃園市東埔里"}],"address":"330 桃園縣桃園市東埔里","P01NAME":"柯娃","LANCOUNT":3,"countyId":"I40"},{"LANDATA":[{"LANDESC":"桃園縣桃園市埔子段埔子小段1735-3地號","SEQ":"1"},{"LANDESC":"桃園縣桃園市埔子段埔子小段1743地號","SEQ":"2"},{"LANDESC":"桃園縣桃園市埔子段埔子小段1735地號","SEQ":"3"}],"IMAGESTAT":"N","licenseStr_3":"(061)建都字第71號","BUILDING_HEIGHT":"","BUILDING_NO":"幢 棟 地上  層 地下  層 共 戶","ADRCOUNT":1,"licenseSeq":"06130056600400050I40","licenseStr_1":"(61)桃縣建都使字第566-5號","issuedDate":"","AREA_TOTAL":"騎樓：14.7㎡，其他：64.84㎡","ADRDATA":[{"SEQ":1,"ADDR":"330 桃園縣桃園市東埔里"}],"address":"330 桃園縣桃園市東埔里","P01NAME":"李文俊","LANCOUNT":3,"countyId":"I40"},{"LANDATA":[{"LANDESC":"桃園縣桃園市埔子段埔子小段1735-3地號","SEQ":"1"},{"LANDESC":"桃園縣桃園市埔子段埔子小段1743地號","SEQ":"2"},{"LANDESC":"桃園縣桃園市埔子段埔子小段1735地號","SEQ":"3"}],"IMAGESTAT":"N","licenseStr_3":"(061)建都字第71號","BUILDING_HEIGHT":"","BUILDING_NO":"幢 棟 地上  層 地下  層 共 戶","ADRCOUNT":1,"licenseSeq":"06130056600400060I40","licenseStr_1":"(61)桃縣建都使字第566-6號","issuedDate":"","AREA_TOTAL":"騎樓：14.7㎡，其他：68.72㎡","ADRDATA":[{"SEQ":1,"ADDR":"330 桃園縣桃園市東埔里"}],"address":"330 桃園縣桃園市東埔里","P01NAME":"陳秀珠","LANCOUNT":3,"countyId":"I40"},{"LANDATA":[{"LANDESC":"桃園縣桃園市埔子段埔子小段1735-3地號","SEQ":"1"},{"LANDESC":"桃園縣桃園市埔子段埔子小段1743地號","SEQ":"2"},{"LANDESC":"桃園縣桃園市埔子段埔子小段1735地號","SEQ":"3"}],"IMAGESTAT":"N","licenseStr_3":"(061)建都字第71號","BUILDING_HEIGHT":"","BUILDING_NO":"幢 棟 地上  層 地下  層 共 戶","ADRCOUNT":1,"licenseSeq":"06130056600400070I40","licenseStr_1":"(61)桃縣建都使字第566-7號","issuedDate":"","AREA_TOTAL":"騎樓：19.7㎡，其他：67.66㎡","ADRDATA":[{"SEQ":1,"ADDR":"330 桃園縣桃園市東埔里"}],"address":"330 桃園縣桃園市東埔里","P01NAME":"呂伯東","LANCOUNT":3,"countyId":"I40"},{"LANDATA":[{"LANDESC":"桃園縣桃園市埔子段埔子小段1735-3地號","SEQ":"1"},{"LANDESC":"桃園縣桃園市埔子段埔子小段1743地號","SEQ":"2"},{"LANDESC":"桃園縣桃園市埔子段埔子小段1735地號","SEQ":"3"}],"IMAGESTAT":"N","licenseStr_3":"(061)建都字第71號","BUILDING_HEIGHT":"","BUILDING_NO":"幢 棟 地上  層 地下  層 共 戶","ADRCOUNT":1,"licenseSeq":"06130056600400080I40","licenseStr_1":"(61)桃縣建都使字第566-8號","issuedDate":"","AREA_TOTAL":"騎樓：14.7㎡，其他：54.17㎡","ADRDATA":[{"SEQ":1,"ADDR":"330 桃園縣桃園市東埔里"}],"address":"330 桃園縣桃園市東埔里","P01NAME":"徐麗華","LANCOUNT":3,"countyId":"I40"},{"LANDATA":[{"LANDESC":"桃園縣桃園市埔子段埔子小段1735-3地號","SEQ":"1"},{"LANDESC":"桃園縣桃園市埔子段埔子小段1743地號","SEQ":"2"},{"LANDESC":"桃園縣桃園市埔子段埔子小段1735地號","SEQ":"3"}],"IMAGESTAT":"N","licenseStr_3":"(061)建都字第71號","BUILDING_HEIGHT":"","BUILDING_NO":"幢 棟 地上  層 地下  層 共 戶","ADRCOUNT":1,"licenseSeq":"06130056600400090I40","licenseStr_1":"(61)桃縣建都使字第566-9號","issuedDate":"","AREA_TOTAL":"騎樓：14.7㎡，其他：54.17㎡","ADRDATA":[{"SEQ":1,"ADDR":"330 桃園縣桃園市東埔里"}],"address":"330 桃園縣桃園市東埔里","P01NAME":"徐戴阿涼","LANCOUNT":3,"countyId":"I40"},{"LANDATA":[{"LANDESC":"桃園縣桃園市埔子段埔子小段1735-3地號","SEQ":"1"},{"LANDESC":"桃園縣桃園市埔子段埔子小段1743地號","SEQ":"2"},{"LANDESC":"桃園縣桃園市埔子段埔子小段1735地號","SEQ":"3"}],"IMAGESTAT":"N","licenseStr_3":"(061)建都字第71號","BUILDING_HEIGHT":"","BUILDING_NO":"幢 棟 地上  層 地下  層 共 戶","ADRCOUNT":1,"licenseSeq":"06130056600400100I40","licenseStr_1":"(61)桃縣建都使字第566-10號","issuedDate":"","AREA_TOTAL":"騎樓：14.7㎡，其他：54.17㎡","ADRDATA":[{"SEQ":1,"ADDR":"330 桃園縣桃園市東埔里"}],"address":"330 桃園縣桃園市東埔里","P01NAME":"呂朝堂","LANCOUNT":3,"countyId":"I40"},{"LANDATA":[{"LANDESC":"桃園縣桃園市埔子段埔子小段1735-3地號","SEQ":"1"},{"LANDESC":"桃園縣桃園市埔子段埔子小段1743地號","SEQ":"2"},{"LANDESC":"桃園縣桃園市埔子段埔子小段1735地號","SEQ":"3"}],"IMAGESTAT":"N","licenseStr_3":"(061)建都字第71號","BUILDING_HEIGHT":"","BUILDING_NO":"幢 棟 地上  層 地下  層 共 戶","ADRCOUNT":1,"licenseSeq":"06130056600400110I40","licenseStr_1":"(61)桃縣建都使字第566-11號","issuedDate":"","AREA_TOTAL":"騎樓：14.7㎡，其他：54.17㎡","ADRDATA":[{"SEQ":1,"ADDR":"330 桃園縣桃園市東埔里"}],"address":"330 桃園縣桃園市東埔里","P01NAME":"郭傳本","LANCOUNT":3,"countyId":"I40"},{"LANDATA":[{"LANDESC":"桃園縣桃園市埔子段埔子小段1735-3地號","SEQ":"1"},{"LANDESC":"桃園縣桃園市埔子段埔子小段1743地號","SEQ":"2"},{"LANDESC":"桃園縣桃園市埔子段埔子小段1735地號","SEQ":"3"}],"IMAGESTAT":"N","licenseStr_3":"(061)建都字第71號","BUILDING_HEIGHT":"","BUILDING_NO":"幢 棟 地上  層 地下  層 共 戶","ADRCOUNT":2,"licenseSeq":"06130056600400120I40","licenseStr_1":"(61)桃縣建都使字第566-12號","issuedDate":"","AREA_TOTAL":"騎樓：10.59㎡，其他：60.41㎡","ADRDATA":[{"SEQ":1,"ADDR":"330 桃園縣桃園市東埔里"},{"SEQ":2,"ADDR":"330 桃園縣桃園市東埔里"}],"address":"330 桃園縣桃園市東埔里","P01NAME":"吳恩篤","LANCOUNT":3,"countyId":"I40"},{"LANDATA":[{"LANDESC":"桃園縣桃園市埔子段埔子小段1735-3地號","SEQ":"1"},{"LANDESC":"桃園縣桃園市埔子段埔子小段1743地號","SEQ":"2"},{"LANDESC":"桃園縣桃園市埔子段埔子小段1735地號","SEQ":"3"}],"IMAGESTAT":"N","licenseStr_3":"(061)建都字第71號","BUILDING_HEIGHT":"","BUILDING_NO":"幢 棟 地上  層 地下  層 共 戶","ADRCOUNT":1,"licenseSeq":"06130056600400130I40","licenseStr_1":"(61)桃縣建都使字第566-13號","issuedDate":"","AREA_TOTAL":"騎樓：10.59㎡，其他：60.41㎡","ADRDATA":[{"SEQ":1,"ADDR":"330 桃園縣桃園市東埔里"}],"address":"330 桃園縣桃園市東埔里","P01NAME":"張林燕","LANCOUNT":3,"countyId":"I40"},{"LANDATA":[{"LANDESC":"桃園縣桃園市埔子段埔子小段1735-3地號","SEQ":"1"},{"LANDESC":"桃園縣桃園市埔子段埔子小段1743地號","SEQ":"2"},{"LANDESC":"桃園縣桃園市埔子段埔子小段1735地號","SEQ":"3"}],"IMAGESTAT":"N","licenseStr_3":"(061)建都字第71號","BUILDING_HEIGHT":"","BUILDING_NO":"幢 棟 地上  層 地下  層 共 戶","ADRCOUNT":1,"licenseSeq":"06130056600400140I40","licenseStr_1":"(61)桃縣建都使字第566-14號","issuedDate":"","AREA_TOTAL":"騎樓：14.7㎡，其他：54.17㎡","ADRDATA":[{"SEQ":1,"ADDR":"330 桃園縣桃園市東埔里"}],"address":"330 桃園縣桃園市東埔里","P01NAME":"楊吳蝦","LANCOUNT":3,"countyId":"I40"},{"LANDATA":[{"LANDESC":"桃園縣桃園市埔子段埔子小段1735-3地號","SEQ":"1"},{"LANDESC":"桃園縣桃園市埔子段埔子小段1743地號","SEQ":"2"},{"LANDESC":"桃園縣桃園市埔子段埔子小段1735地號","SEQ":"3"}],"IMAGESTAT":"N","licenseStr_3":"(061)建都字第71號","BUILDING_HEIGHT":"","BUILDING_NO":"幢 棟 地上  層 地下  層 共 戶","ADRCOUNT":1,"licenseSeq":"06130056600400150I40","licenseStr_1":"(61)桃縣建都使字第566-15號","issuedDate":"","AREA_TOTAL":"騎樓：14.7㎡，其他：79.88㎡","ADRDATA":[{"SEQ":1,"ADDR":"330 桃園縣桃園市東埔里"}],"address":"330 桃園縣桃園市東埔里","P01NAME":"伍王春美","LANCOUNT":3,"countyId":"I40"},{"LANDATA":[{"LANDESC":"桃園縣桃園市埔子段埔子小段1735-3地號","SEQ":"1"},{"LANDESC":"桃園縣桃園市埔子段埔子小段1743地號","SEQ":"2"},{"LANDESC":"桃園縣桃園市埔子段埔子小段1735地號","SEQ":"3"}],"IMAGESTAT":"N","licenseStr_3":"(061)建都字第71號","BUILDING_HEIGHT":"","BUILDING_NO":"幢 棟 地上  層 地下  層 共 戶","ADRCOUNT":1,"licenseSeq":"06130056600400160I40","licenseStr_1":"(61)桃縣建都使字第566-16號","issuedDate":"","AREA_TOTAL":"騎樓：14.7㎡，其他：84.73㎡","ADRDATA":[{"SEQ":1,"ADDR":"330 桃園縣桃園市東埔里"}],"address":"330 桃園縣桃園市東埔里","P01NAME":"王陳雲","LANCOUNT":3,"countyId":"I40"},{"LANDATA":[{"LANDESC":"桃園縣桃園市埔子段埔子小段1735-3地號","SEQ":"1"},{"LANDESC":"桃園縣桃園市埔子段埔子小段1743地號","SEQ":"2"},{"LANDESC":"桃園縣桃園市埔子段埔子小段1735地號","SEQ":"3"}],"IMAGESTAT":"N","licenseStr_3":"(061)建都字第71號","BUILDING_HEIGHT":"","BUILDING_NO":"幢 棟 地上  層 地下  層 共 戶","ADRCOUNT":1,"licenseSeq":"06130056600400170I40","licenseStr_1":"(61)桃縣建都使字第566-17號","issuedDate":"","AREA_TOTAL":"騎樓：0㎡，其他：59.17㎡","ADRDATA":[{"SEQ":1,"ADDR":"330 桃園縣桃園市東埔里"}],"address":"330 桃園縣桃園市東埔里","P01NAME":"簡黃緞","LANCOUNT":3,"countyId":"I40"},{"LANDATA":[{"LANDESC":"桃園縣桃園市埔子段埔子小段1735-3地號","SEQ":"1"},{"LANDESC":"桃園縣桃園市埔子段埔子小段1743地號","SEQ":"2"},{"LANDESC":"桃園縣桃園市埔子段埔子小段1735地號","SEQ":"3"}],"IMAGESTAT":"N","licenseStr_3":"(061)建都字第71號","BUILDING_HEIGHT":"","BUILDING_NO":"幢 棟 地上  層 地下  層 共 戶","ADRCOUNT":1,"licenseSeq":"06130056600400180I40","licenseStr_1":"(61)桃縣建都使字第566-18號","issuedDate":"","AREA_TOTAL":"騎樓：0㎡，其他：59.17㎡","ADRDATA":[{"SEQ":1,"ADDR":"330 桃園縣桃園市東埔里"}],"address":"330 桃園縣桃園市東埔里","P01NAME":"李阿淡","LANCOUNT":3,"countyId":"I40"},{"LANDATA":[{"LANDESC":"桃園縣桃園市埔子段埔子小段1735-3地號","SEQ":"1"},{"LANDESC":"桃園縣桃園市埔子段埔子小段1743地號","SEQ":"2"},{"LANDESC":"桃園縣桃園市埔子段埔子小段1735地號","SEQ":"3"}],"IMAGESTAT":"N","licenseStr_3":"(061)建都字第71號","BUILDING_HEIGHT":"","BUILDING_NO":"幢 棟 地上  層 地下  層 共 戶","ADRCOUNT":1,"licenseSeq":"06130056600400190I40","licenseStr_1":"(61)桃縣建都使字第566-19號","issuedDate":"","AREA_TOTAL":"騎樓：0㎡，其他：59.17㎡","ADRDATA":[{"SEQ":1,"ADDR":"330 桃園縣桃園市東埔里"}],"address":"330 桃園縣桃園市東埔里","P01NAME":"徐粉","LANCOUNT":3,"countyId":"I40"},{"LANDATA":[{"LANDESC":"桃園縣桃園市埔子段埔子小段1735-3地號","SEQ":"1"},{"LANDESC":"桃園縣桃園市埔子段埔子小段1743地號","SEQ":"2"},{"LANDESC":"桃園縣桃園市埔子段埔子小段1735地號","SEQ":"3"}],"IMAGESTAT":"N","licenseStr_3":"(061)建都字第71號","BUILDING_HEIGHT":"","BUILDING_NO":"幢 棟 地上  層 地下  層 共 戶","ADRCOUNT":1,"licenseSeq":"06130056600400200I40","licenseStr_1":"(61)桃縣建都使字第566-20號","issuedDate":"","AREA_TOTAL":"騎樓：0㎡，其他：59.17㎡","ADRDATA":[{"SEQ":1,"ADDR":"330 桃園縣桃園市東埔里"}],"address":"330 桃園縣桃園市東埔里","P01NAME":"廖全","LANCOUNT":3,"countyId":"I40"},{"LANDATA":[{"LANDESC":"桃園縣桃園市埔子段埔子小段1735-3地號","SEQ":"1"},{"LANDESC":"桃園縣桃園市埔子段埔子小段1743地號","SEQ":"2"},{"LANDESC":"桃園縣桃園市埔子段埔子小段1735地號","SEQ":"3"}],"IMAGESTAT":"N","licenseStr_3":"(061)建都字第71號","BUILDING_HEIGHT":"","BUILDING_NO":"幢 棟 地上  層 地下  層 共 戶","ADRCOUNT":1,"licenseSeq":"06130056600400210I40","licenseStr_1":"(61)桃縣建都使字第566-21號","issuedDate":"","AREA_TOTAL":"騎樓：0㎡，其他：59.17㎡","ADRDATA":[{"SEQ":1,"ADDR":"330 桃園縣桃園市東埔里"}],"address":"330 桃園縣桃園市東埔里","P01NAME":"沈照雄","LANCOUNT":3,"countyId":"I40"},{"LANDATA":[{"LANDESC":"桃園縣桃園市埔子段埔子小段1735-3地號","SEQ":"1"},{"LANDESC":"桃園縣桃園市埔子段埔子小段1743地號","SEQ":"2"},{"LANDESC":"桃園縣桃園市埔子段埔子小段1735地號","SEQ":"3"}],"IMAGESTAT":"N","licenseStr_3":"(061)建都字第71號","BUILDING_HEIGHT":"","BUILDING_NO":"幢 棟 地上  層 地下  層 共 戶","ADRCOUNT":1,"licenseSeq":"06130056600400220I40","licenseStr_1":"(61)桃縣建都使字第566-22號","issuedDate":"","AREA_TOTAL":"騎樓：0㎡，其他：78.09㎡","ADRDATA":[{"SEQ":1,"ADDR":"330 桃園縣桃園市東埔里"}],"address":"330 桃園縣桃園市東埔里","P01NAME":"卓丙子","LANCOUNT":3,"countyId":"I40"},{"LANDATA":[{"LANDESC":"桃園縣桃園市埔子段埔子小段1735-3地號","SEQ":"1"},{"LANDESC":"桃園縣桃園市埔子段埔子小段1743地號","SEQ":"2"},{"LANDESC":"桃園縣桃園市埔子段埔子小段1735地號","SEQ":"3"}],"IMAGESTAT":"N","licenseStr_3":"(061)建都字第71號","BUILDING_HEIGHT":"","BUILDING_NO":"幢 棟 地上  層 地下  層 共 戶","ADRCOUNT":1,"licenseSeq":"06130056600400230I40","licenseStr_1":"(61)桃縣建都使字第566-23號","issuedDate":"","AREA_TOTAL":"騎樓：14.7㎡，其他：60.96㎡","ADRDATA":[{"SEQ":1,"ADDR":"330 桃園縣桃園市東埔里"}],"address":"330 桃園縣桃園市東埔里","P01NAME":"陳鄭?","LANCOUNT":3,"countyId":"I40"},{"LANDATA":[{"LANDESC":"桃園縣桃園市埔子段埔子小段1735-3地號","SEQ":"1"},{"LANDESC":"桃園縣桃園市埔子段埔子小段1743地號","SEQ":"2"},{"LANDESC":"桃園縣桃園市埔子段埔子小段1735地號","SEQ":"3"}],"IMAGESTAT":"N","licenseStr_3":"(061)建都字第71號","BUILDING_HEIGHT":"","BUILDING_NO":"幢 棟 地上  層 地下  層 共 戶","ADRCOUNT":1,"licenseSeq":"06130056600400240I40","licenseStr_1":"(61)桃縣建都使字第566-24號","issuedDate":"","AREA_TOTAL":"騎樓：14.7㎡，其他：78.42㎡","ADRDATA":[{"SEQ":1,"ADDR":"330 桃園縣桃園市東埔里"}],"address":"330 桃園縣桃園市東埔里","P01NAME":"陳徐血","LANCOUNT":3,"countyId":"I40"},{"LANDATA":[{"LANDESC":"桃園縣桃園市埔子段埔子小段1735-3地號","SEQ":"1"},{"LANDESC":"桃園縣桃園市埔子段埔子小段1743地號","SEQ":"2"},{"LANDESC":"桃園縣桃園市埔子段埔子小段1735地號","SEQ":"3"}],"IMAGESTAT":"N","licenseStr_3":"(061)建都字第71號","BUILDING_HEIGHT":"","BUILDING_NO":"幢 棟 地上  層 地下  層 共 戶","ADRCOUNT":1,"licenseSeq":"06130056600400250I40","licenseStr_1":"(61)桃縣建都使字第566-25號","issuedDate":"","AREA_TOTAL":"騎樓：0㎡，其他：59.16㎡","ADRDATA":[{"SEQ":1,"ADDR":"330 桃園縣桃園市東埔里"}],"address":"330 桃園縣桃園市東埔里","P01NAME":"連國林","LANCOUNT":3,"countyId":"I40"},{"LANDATA":[{"LANDESC":"桃園縣桃園市埔子段埔子小段1735-3地號","SEQ":"1"},{"LANDESC":"桃園縣桃園市埔子段埔子小段1743地號","SEQ":"2"},{"LANDESC":"桃園縣桃園市埔子段埔子小段1735地號","SEQ":"3"}],"IMAGESTAT":"N","licenseStr_3":"(061)建都字第71號","BUILDING_HEIGHT":"","BUILDING_NO":"幢 棟 地上  層 地下  層 共 戶","ADRCOUNT":1,"licenseSeq":"06130056600400260I40","licenseStr_1":"(61)桃縣建都使字第566-26號","issuedDate":"","AREA_TOTAL":"騎樓：0㎡，其他：64.02㎡","ADRDATA":[{"SEQ":1,"ADDR":"330 桃園縣桃園市東埔里"}],"address":"330 桃園縣桃園市東埔里","P01NAME":"陳鄭?","LANCOUNT":3,"countyId":"I40"},{"LANDATA":[{"LANDESC":"桃園縣桃園市埔子段埔子小段1735-3地號","SEQ":"1"},{"LANDESC":"桃園縣桃園市埔子段埔子小段1743地號","SEQ":"2"},{"LANDESC":"桃園縣桃園市埔子段埔子小段1735地號","SEQ":"3"}],"IMAGESTAT":"N","licenseStr_3":"(061)建都字第71號","BUILDING_HEIGHT":"","BUILDING_NO":"幢 棟 地上  層 地下  層 共 戶","ADRCOUNT":1,"licenseSeq":"06130056600400270I40","licenseStr_1":"(61)桃縣建都使字第566-27號","issuedDate":"","AREA_TOTAL":"騎樓：0㎡，其他：87.92㎡","ADRDATA":[{"SEQ":1,"ADDR":"330 桃園縣桃園市東埔里"}],"address":"330 桃園縣桃園市東埔里","P01NAME":"吳德坤","LANCOUNT":3,"countyId":"I40"},{"LANDATA":[{"LANDESC":"桃園縣桃園市埔子段埔子小段1735-3地號","SEQ":"1"},{"LANDESC":"桃園縣桃園市埔子段埔子小段1743地號","SEQ":"2"},{"LANDESC":"桃園縣桃園市埔子段埔子小段1735地號","SEQ":"3"}],"IMAGESTAT":"N","licenseStr_3":"(061)建都字第71號","BUILDING_HEIGHT":"","BUILDING_NO":"幢 棟 地上  層 地下  層 共 戶","ADRCOUNT":1,"licenseSeq":"06130056600400280I40","licenseStr_1":"(61)桃縣建都使字第566-28號","issuedDate":"","AREA_TOTAL":"騎樓：0㎡，其他：77.6㎡","ADRDATA":[{"SEQ":1,"ADDR":"330 桃園縣桃園市東埔里"}],"address":"330 桃園縣桃園市東埔里","P01NAME":"陳鄭?","LANCOUNT":3,"countyId":"I40"},{"LANDATA":[{"LANDESC":"桃園縣桃園市埔子段埔子小段1735-3地號","SEQ":"1"},{"LANDESC":"桃園縣桃園市埔子段埔子小段1743地號","SEQ":"2"},{"LANDESC":"桃園縣桃園市埔子段埔子小段1735地號","SEQ":"3"}],"IMAGESTAT":"N","licenseStr_3":"(061)建都字第71號","BUILDING_HEIGHT":"","BUILDING_NO":"幢 棟 地上  層 地下  層 共 戶","ADRCOUNT":1,"licenseSeq":"06130056600400290I40","licenseStr_1":"(61)桃縣建都使字第566-29號","issuedDate":"","AREA_TOTAL":"騎樓：0㎡，其他：73.24㎡","ADRDATA":[{"SEQ":1,"ADDR":"330 桃園縣桃園市東埔里"}],"address":"330 桃園縣桃園市東埔里","P01NAME":"陳鄭?","LANCOUNT":3,"countyId":"I40"},{"LANDATA":[{"LANDESC":"桃園縣桃園市桃園段中南小段50地號","SEQ":"1"},{"LANDESC":"桃園縣桃園市桃園段中南小段46-10地號","SEQ":"2"},{"LANDESC":"桃園縣桃園市桃園段中南小段45-3地號","SEQ":"3"}],"IMAGESTAT":"N","licenseStr_3":"(060)建都字第2206號","BUILDING_HEIGHT":"","BUILDING_NO":"幢 棟 地上  層 地下  層 共 戶","ADRCOUNT":1,"licenseSeq":"06130056600450000I40","licenseStr_1":"(61)桃府建都使字第566號","issuedDate":"061/04/24","AREA_TOTAL":"騎樓：0㎡，其他：0㎡","ADRDATA":[{"SEQ":1,"ADDR":"330 桃園縣桃園市中北里永樂路"}],"address":"330 桃園縣桃園市中北里永樂路","P01NAME":"簡木生、陳文翼、陳茂利、陳游美枝","LANCOUNT":3,"countyId":"I40"}]}


