

{"MSG":"搜尋到資料有2筆","count":2,"licenseData":[{"LANDATA":[{"LANDESC":"臺中市東區旱溪段340-28地號","SEQ":"1"}],"IMAGESTAT":"N","licenseStr_3":"67中工建建字第01220號","BUILDING_HEIGHT":"7.52Ｍ","BUILDING_NO":"幢 1棟 地上 2 層 地下  層 共 1戶","ADRCOUNT":1,"licenseSeq":"06730122000","licenseStr_1":"67中工建使字第01220號","issuedDate":"067/10/07","AREA_TOTAL":"騎樓：40㎡，其他：191㎡","ADRDATA":[{"SEQ":1,"ADDR":"401 臺中市東區十甲路102-3號"}],"address":"401 臺中市東區十甲路102-3號","P01NAME":"楊鑄造廠 代表人: 楊信男","LANCOUNT":1,"countyId":"I80"},{"LANDATA":[{"LANDESC":"","SEQ":"1"},{"LANDESC":"","SEQ":"1"}],"IMAGESTAT":"N","licenseStr_3":"(067)建都營字第1220號","BUILDING_HEIGHT":"6.8Ｍ","BUILDING_NO":"幢 1棟 地上 1 層 地下  層 共 1戶","ADRCOUNT":3,"licenseSeq":"06730122000000000I90","licenseStr_1":"(67)建都營使字第1220號","issuedDate":"067/06/05","AREA_TOTAL":"騎樓：0㎡，其他：1460㎡","ADRDATA":[{"SEQ":1,"ADDR":"434 臺中市龍井區忠和村中央路海尾仔巷17-1號"},{"SEQ":2,"ADDR":"434 臺中市龍井區忠和村中央路海尾仔巷17-1號"},{"SEQ":3,"ADDR":"434 臺中市龍井區忠和村中央路海尾仔巷17-1號"}],"address":"434 臺中市龍井區忠和村中央路海尾仔巷17-1號","P01NAME":"","LANCOUNT":2,"countyId":"I90"}]}


